{"Version":"0.0.0","Data":{"WorldObjectLocatorManager":"{\"Version\":\"0.0.0\",\"SerializedStates\":[{\"Key\":\"A0E7E5FFEEFD0000DA865D00\",\"Value\":1},{\"Key\":\"CEF0E5FF6FFD0000BD9A5D00\",\"Value\":1},{\"Key\":\"7806E6FFECF60000BA925D00\",\"Value\":1},{\"Key\":\"F8DAE5FF1D020100B7855D00\",\"Value\":1},{\"Key\":\"EBCAE6FF955E010022A35B00\",\"Value\":1},{\"Key\":\"DEA2E6FFC3610100C7A15B00\",\"Value\":1},{\"Key\":\"E2A0E6FF4A62010051895B00\",\"Value\":1},{\"Key\":\"17A3E6FFE2610100D47B5B00\",\"Value\":1},{\"Key\":\"12B5E6FF27600100857A5B00\",\"Value\":1},{\"Key\":\"A0B9E6FF2C600100B9A35B00\",\"Value\":1},{\"Key\":\"90C0E6FFB35F0100D48D5B00\",\"Value\":1},{\"Key\":\"06D2DFFF5AB90500EA0D2100\",\"Value\":1},{\"Key\":\"B2C6D4FF904C0600A7F51A00\",\"Value\":1},{\"Key\":\"CFC2D4FF904C060013E21A00\",\"Value\":1},{\"Key\":\"89AED4FFA54C06008AD31A00\",\"Value\":1},{\"Key\":\"C7C2D4FF6D4D0600EABB1A00\",\"Value\":1},{\"Key\":\"D3B5D4FF0E4D060004B01A00\",\"Value\":1},{\"Key\":\"28CAD4FF554F06001CA71A00\",\"Value\":1},{\"Key\":\"51B4D4FF924E06009E981A00\",\"Value\":1},{\"Key\":\"EA4DD4FF904C060015341C00\",\"Value\":1},{\"Key\":\"E34AD4FF904C0600A21C1C00\",\"Value\":1},{\"Key\":\"B139D4FF904C060081261C00\",\"Value\":1},{\"Key\":\"491DD4FF904C060043171C00\",\"Value\":1},{\"Key\":\"F71ED4FF904C0600DB311C00\",\"Value\":1},{\"Key\":\"0311D4FF904C0600BF331C00\",\"Value\":1},{\"Key\":\"57B9D0FF28D909009716F2FF\",\"Value\":1},{\"Key\":\"8263D2FF4DDD0900858EF2FF\",\"Value\":1},{\"Key\":\"3664D2FFB0E3090012BDF2FF\",\"Value\":1},{\"Key\":\"C472D2FFD8E2090056BEF2FF\",\"Value\":1},{\"Key\":\"0663D2FF0BE5090051D1F2FF\",\"Value\":1},{\"Key\":\"D462D2FF2CE5090050DEF2FF\",\"Value\":1},{\"Key\":\"8771D2FF2CE509009C09F3FF\",\"Value\":1},{\"Key\":\"AB76D2FF2CE5090052EEF2FF\",\"Value\":1},{\"Key\":\"6173D2FF2CE50900BF2CF3FF\",\"Value\":1},{\"Key\":\"1F63D2FF2CE5090090F1F2FF\",\"Value\":1},{\"Key\":\"6D5ED2FF2CE509009509F3FF\",\"Value\":1},{\"Key\":\"72BED2FFF9E10900A5D8F2FF\",\"Value\":1},{\"Key\":\"4473D2FF11E409001C45F3FF\",\"Value\":1},{\"Key\":\"FA76D2FFE2E3090011CCF2FF\",\"Value\":1},{\"Key\":\"5B85D2FFC0E1090008BEF2FF\",\"Value\":1},{\"Key\":\"6085D2FF52E3090087CBF2FF\",\"Value\":1},{\"Key\":\"0584D2FF0BDE09007AA7F2FF\",\"Value\":1},{\"Key\":\"A284D2FFEAE4090058DFF2FF\",\"Value\":1},{\"Key\":\"F59DD2FF2CE5090019F4F2FF\",\"Value\":1},{\"Key\":\"50AAD2FF0FE50900A4F5F2FF\",\"Value\":1},{\"Key\":\"4B8AD2FF2CE509009E05F3FF\",\"Value\":1},{\"Key\":\"C89CD2FF2CE50900F304F3FF\",\"Value\":1},{\"Key\":\"679BD2FFDAE40900C4E4F2FF\",\"Value\":1},{\"Key\":\"7B7BD2FF32E30900BB51F3FF\",\"Value\":1},{\"Key\":\"5CA0D2FF67E1090024C7F2FF\",\"Value\":1},{\"Key\":\"68BDD2FFBFDC09006CBCF2FF\",\"Value\":1},{\"Key\":\"E1D2D2FFFAE009000DDEF2FF\",\"Value\":1},{\"Key\":\"7DBED2FF2CE50900E104F3FF\",\"Value\":1},{\"Key\":\"28C3D2FF2CE509005025F3FF\",\"Value\":1},{\"Key\":\"4BEBD1FF2CE50900BF07F3FF\",\"Value\":1},{\"Key\":\"E1DAD1FF2CE509003204F3FF\",\"Value\":1},{\"Key\":\"BE64D1FF2CE50900A30CF3FF\",\"Value\":1},{\"Key\":\"44EAD2FF54DA0900E3CEF2FF\",\"Value\":1},{\"Key\":\"4901D2FF22E509002604F3FF\",\"Value\":1},{\"Key\":\"3512D2FF2CE5090056F2F2FF\",\"Value\":1},{\"Key\":\"28CAD1FF2CE5090098F7F2FF\",\"Value\":1},{\"Key\":\"4A05D2FFBFE40900171BF3FF\",\"Value\":1},{\"Key\":\"00F1D1FF2CE50900501DF3FF\",\"Value\":1},{\"Key\":\"71EFD1FF22E209002531F3FF\",\"Value\":1},{\"Key\":\"07FFD1FF58E40900B62BF3FF\",\"Value\":1},{\"Key\":\"76D2D2FFBEDE09008DD1F2FF\",\"Value\":1},{\"Key\":\"FC59D1FF2CE50900980BF3FF\",\"Value\":1},{\"Key\":\"E097D2FF6CDF0900FBB8F2FF\",\"Value\":1},{\"Key\":\"1CABD2FF0CDE0900D1B8F2FF\",\"Value\":1},{\"Key\":\"AA19D2FF1EE10900A09CF2FF\",\"Value\":1},{\"Key\":\"CA1DD2FF29DE09006181F2FF\",\"Value\":1},{\"Key\":\"2106D2FF6CDE0900A091F2FF\",\"Value\":1},{\"Key\":\"4711D2FFFADD09008568F2FF\",\"Value\":1},{\"Key\":\"0603D2FF69DC0900C675F2FF\",\"Value\":1},{\"Key\":\"CEF8D1FF87DB09009B68F2FF\",\"Value\":1},{\"Key\":\"D7DFD1FF87D609009978F2FF\",\"Value\":1},{\"Key\":\"0AE4D1FF59DB0900B18DF2FF\",\"Value\":1},{\"Key\":\"961CD2FFA2E4090091C7F2FF\",\"Value\":1},{\"Key\":\"7DFED1FFABE2090023BCF2FF\",\"Value\":1},{\"Key\":\"9628D2FF5AE40900A142F3FF\",\"Value\":1},{\"Key\":\"DA13D2FFBCE30900A547F3FF\",\"Value\":1},{\"Key\":\"C006D2FF60E309007E42F3FF\",\"Value\":1},{\"Key\":\"231DD2FF4DE00900DC84F3FF\",\"Value\":1},{\"Key\":\"5D15D2FFE0DD0900CB9CF3FF\",\"Value\":1},{\"Key\":\"3E5ED2FF88E109007B68F3FF\",\"Value\":1},{\"Key\":\"40FFD1FF4FE309008C51F3FF\",\"Value\":1},{\"Key\":\"F18DD2FFD3E00900A96EF3FF\",\"Value\":3},{\"Key\":\"4335D2FF39E309004D5FF3FF\",\"Value\":1},{\"Key\":\"F028D2FF86E10900CD74F3FF\",\"Value\":1},{\"Key\":\"DD37D2FFF7DE0900E48BF3FF\",\"Value\":1},{\"Key\":\"E940D2FFC4DE09006B8AF3FF\",\"Value\":1},{\"Key\":\"97F0D1FF9FE4090075DEF2FF\",\"Value\":1},{\"Key\":\"1AF2D1FFE5E3090045CFF2FF\",\"Value\":1},{\"Key\":\"7FC8D1FF2CE509003017F3FF\",\"Value\":1},{\"Key\":\"D8DCD1FF94E3090099D1F2FF\",\"Value\":1},{\"Key\":\"61D8D1FFAEE1090027BAF2FF\",\"Value\":1},{\"Key\":\"94AAD2FF42DA0900E4A9F2FF\",\"Value\":1},{\"Key\":\"4DEBD1FF13E20900EDBAF2FF\",\"Value\":1},{\"Key\":\"E1C8D1FFCFD809007585F2FF\",\"Value\":1},{\"Key\":\"CF8AD1FFD1E4090036E3F2FF\",\"Value\":1},{\"Key\":\"6435D1FF43E40900BFCBF2FF\",\"Value\":1},{\"Key\":\"AA8AD2FF26D909005396F2FF\",\"Value\":1},{\"Key\":\"954BD2FF2CE509004405F3FF\",\"Value\":1},{\"Key\":\"F7CBD1FFBED20900146EF2FF\",\"Value\":1},{\"Key\":\"520FD3FF90DB0900D2DEF2FF\",\"Value\":1},{\"Key\":\"CDFBD2FFD5DC09007DDEF2FF\",\"Value\":1},{\"Key\":\"4E0FD3FF1AE10900E5F1F2FF\",\"Value\":1},{\"Key\":\"5FF5D2FF2CE509001039F3FF\",\"Value\":1},{\"Key\":\"763DD2FF2CE509000905F3FF\",\"Value\":1},{\"Key\":\"BC21D2FFB0E30900711BF3FF\",\"Value\":1},{\"Key\":\"5E2DD2FFA0C30900D1FDF3FF\",\"Value\":1},{\"Key\":\"F88FD2FF2CE50900CB2CF3FF\",\"Value\":1},{\"Key\":\"2BA3D2FFC5E409007E3FF3FF\",\"Value\":1},{\"Key\":\"992BD3FF37E009005C8FF3FF\",\"Value\":1},{\"Key\":\"E21DD3FFDBD60900F5B9F3FF\",\"Value\":1},{\"Key\":\"5A00D2FFCCE4090046DEF2FF\",\"Value\":1},{\"Key\":\"8FDED1FFD2E4090059E3F2FF\",\"Value\":1},{\"Key\":\"07CCD1FF63E30900DACEF2FF\",\"Value\":1},{\"Key\":\"3CB2D1FF2CE509006C06F3FF\",\"Value\":1},{\"Key\":\"138FD1FF2CE509001D04F3FF\",\"Value\":1},{\"Key\":\"8566D1FFE4E4090006D9F2FF\",\"Value\":1},{\"Key\":\"8A36D2FFF7C009003122F4FF\",\"Value\":1},{\"Key\":\"2511D2FFEED30900B7CFF3FF\",\"Value\":1},{\"Key\":\"E413D2FF48C5090042FEF3FF\",\"Value\":1},{\"Key\":\"2372D2FF0BC40900E9F8F4FF\",\"Value\":1},{\"Key\":\"4174D2FF26C409006EE7F4FF\",\"Value\":1},{\"Key\":\"CEA4D2FF10C1090051CEF4FF\",\"Value\":1},{\"Key\":\"42AED2FFA4C10900E2DAF4FF\",\"Value\":1},{\"Key\":\"E668D2FFD5C30900D6F8F4FF\",\"Value\":1},{\"Key\":\"A080D2FF4BC30900330FF5FF\",\"Value\":1},{\"Key\":\"CB72D2FFCEBA0900B632F4FF\",\"Value\":1},{\"Key\":\"302BD2FFE8C009005611F4FF\",\"Value\":1},{\"Key\":\"2C32D2FF0BDD0900689BF3FF\",\"Value\":1},{\"Key\":\"793DD2FF08C109006036F4FF\",\"Value\":1},{\"Key\":\"6645D2FFBEDB0900E59BF3FF\",\"Value\":1},{\"Key\":\"494BD2FFDBE409002BBDF2FF\",\"Value\":1},{\"Key\":\"515AD2FF89D90900629FF3FF\",\"Value\":1},{\"Key\":\"3137D3FF68E309007313F3FF\",\"Value\":1},{\"Key\":\"A640D3FF5FE40900E920F3FF\",\"Value\":1},{\"Key\":\"AB1ED3FF8FE409007913F3FF\",\"Value\":1},{\"Key\":\"4120D3FF8BE0090077F1F2FF\",\"Value\":1},{\"Key\":\"DBEED1FF24E5090006F1F2FF\",\"Value\":1},{\"Key\":\"536CD3FF8ADE09000A17F3FF\",\"Value\":1},{\"Key\":\"0185D3FFF6E209006A08F3FF\",\"Value\":1},{\"Key\":\"59A3D2FF91C7090072EAF3FF\",\"Value\":1},{\"Key\":\"972DD2FF1FD4090048C7F3FF\",\"Value\":1},{\"Key\":\"1302D3FFC6D509004ECDF2FF\",\"Value\":1},{\"Key\":\"FFE5D2FF17D609009DBEF2FF\",\"Value\":1},{\"Key\":\"85D3D2FF19D70900C7B7F2FF\",\"Value\":1},{\"Key\":\"803DD3FF2CE509009D48F3FF\",\"Value\":1},{\"Key\":\"444FD3FF2CE509007C43F3FF\",\"Value\":1},{\"Key\":\"E57CD1FF6BDA09001193F2FF\",\"Value\":1},{\"Key\":\"6DEFD0FF2CE509009EEFF2FF\",\"Value\":1},{\"Key\":\"021ED1FFB9D50900A36BF2FF\",\"Value\":1},{\"Key\":\"3297D2FFF4DB090033A9F2FF\",\"Value\":1},{\"Key\":\"4B98D2FF4BD70900C097F2FF\",\"Value\":1},{\"Key\":\"060ED0FF5C22090053E3F5FF\",\"Value\":3},{\"Key\":\"640AD3FF32E309001183F3FF\",\"Value\":1},{\"Key\":\"702BD2FF2CE50900F1F3F2FF\",\"Value\":1},{\"Key\":\"450BD3FF2CE50900AB20F3FF\",\"Value\":1},{\"Key\":\"4F11D3FFE7E409004716F3FF\",\"Value\":1},{\"Key\":\"A500D3FF27E509002314F3FF\",\"Value\":1},{\"Key\":\"2FE1D2FFEDE30900AE77F3FF\",\"Value\":1},{\"Key\":\"91D4D2FF0CD10900A2D6F3FF\",\"Value\":1},{\"Key\":\"D5CAD2FFD5D60900E9BDF3FF\",\"Value\":1},{\"Key\":\"101ED3FF2CE509000626F3FF\",\"Value\":1},{\"Key\":\"ABECD2FFB1DF09005CA3F3FF\",\"Value\":1},{\"Key\":\"13C1D2FFFAD1090094CCF3FF\",\"Value\":1},{\"Key\":\"CBC2D2FFD7E40900CF4CF3FF\",\"Value\":1},{\"Key\":\"A1D4D2FF8BE40900215CF3FF\",\"Value\":1},{\"Key\":\"66E3D2FFABD80900D0BDF3FF\",\"Value\":1},{\"Key\":\"88C5D2FF96E209006979F3FF\",\"Value\":1},{\"Key\":\"21A3D2FF57E309004858F3FF\",\"Value\":1},{\"Key\":\"75E5D2FF20E50900B850F3FF\",\"Value\":1},{\"Key\":\"F4C7D2FF33E10900C690F3FF\",\"Value\":1},{\"Key\":\"23C5D2FF44CA09002FF4F3FF\",\"Value\":1},{\"Key\":\"8CABD2FF94CB0900D1DBF3FF\",\"Value\":1},{\"Key\":\"2C3FD2FF2CE5090072E3F2FF\",\"Value\":1},{\"Key\":\"BBF7D1FF3AD909000BBEF3FF\",\"Value\":1},{\"Key\":\"7034D2FFDDC6090020F3F3FF\",\"Value\":1},{\"Key\":\"9311D2FFADDF09000F8EF3FF\",\"Value\":1},{\"Key\":\"38E9D2FFBADF0900EFE3F2FF\",\"Value\":1},{\"Key\":\"D151D2FF2CE50900A72CF3FF\",\"Value\":1},{\"Key\":\"848AD2FF34DD0900858AF3FF\",\"Value\":1},{\"Key\":\"BA0CD3FF2CE509005D3DF3FF\",\"Value\":1},{\"Key\":\"7AB2D3FF39E50900045EF3FF\",\"Value\":1},{\"Key\":\"5A67D3FF6FDC09006FA2F3FF\",\"Value\":1},{\"Key\":\"7E8AD3FF03DC0900CAC2F3FF\",\"Value\":1},{\"Key\":\"B2B1D3FFCAE70900AED0F3FF\",\"Value\":1},{\"Key\":\"D3B2D3FF64E9090097C0F3FF\",\"Value\":1},{\"Key\":\"D7A2D3FF7EE30900ADCCF3FF\",\"Value\":1},{\"Key\":\"BB9BD3FF78E209001AB5F3FF\",\"Value\":1},{\"Key\":\"B18DD3FF83DB09001D00F4FF\",\"Value\":1},{\"Key\":\"1880D2FF52D90900579EF3FF\",\"Value\":1},{\"Key\":\"2A4FD3FF20DF09007504F3FF\",\"Value\":1},{\"Key\":\"075CD3FF2CE50900F02FF3FF\",\"Value\":1},{\"Key\":\"4937D3FF2BE50900395DF3FF\",\"Value\":1},{\"Key\":\"542AD3FF2CE50900785BF3FF\",\"Value\":3},{\"Key\":\"7420D3FF2CE509007450F3FF\",\"Value\":1},{\"Key\":\"626FD3FF2CE50900043FF3FF\",\"Value\":1},{\"Key\":\"8921D3FFBBE40900266AF3FF\",\"Value\":1},{\"Key\":\"AA2CD3FFC8D709003FD7F3FF\",\"Value\":1},{\"Key\":\"480FD3FFD6E309005E79F3FF\",\"Value\":1},{\"Key\":\"B074D3FFB7DD0900A3C0F2FF\",\"Value\":1},{\"Key\":\"FE4ED3FF00D5090069C4F2FF\",\"Value\":1},{\"Key\":\"5580D3FF47E2090056E1F2FF\",\"Value\":1},{\"Key\":\"EC73D3FFEBE00900DEE4F2FF\",\"Value\":1},{\"Key\":\"6435D3FF4AE40900A969F3FF\",\"Value\":1},{\"Key\":\"4BCBD3FFA3EB0900ACD9F2FF\",\"Value\":1},{\"Key\":\"5ABDD3FF2CE509005ED8F2FF\",\"Value\":1},{\"Key\":\"71B7D3FF2CE5090084EFF2FF\",\"Value\":1},{\"Key\":\"8C9CD3FFC6E409000BCDF2FF\",\"Value\":1},{\"Key\":\"ABA0D3FFB1E409006BEFF2FF\",\"Value\":1},{\"Key\":\"429CD3FFA1E409006AE5F2FF\",\"Value\":1},{\"Key\":\"E136D3FFA8DA0900A4DBF2FF\",\"Value\":1},{\"Key\":\"A545D3FF29DC0900E8A4F3FF\",\"Value\":1},{\"Key\":\"E1BFD3FF7ADB0900E751F4FF\",\"Value\":1},{\"Key\":\"D84ED3FF3EDC0900D4A3F3FF\",\"Value\":1},{\"Key\":\"E5C2D2FF64E40900D3F1F2FF\",\"Value\":1},{\"Key\":\"4812D3FFF2D7090043C1F3FF\",\"Value\":1},{\"Key\":\"F1A5D3FFD9E00900E3F1F3FF\",\"Value\":1},{\"Key\":\"BCC9D3FF69DC0900AB3BF4FF\",\"Value\":1},{\"Key\":\"04E2D3FFCCDF0900FE4EF4FF\",\"Value\":1},{\"Key\":\"DB03D3FF21DE0900A2A7F3FF\",\"Value\":3},{\"Key\":\"47C1D2FFCBDC0900DAA6F3FF\",\"Value\":3},{\"Key\":\"4E06D3FFE1D309000DD8F3FF\",\"Value\":1},{\"Key\":\"B4FAD2FFF0C90900EE18F4FF\",\"Value\":1},{\"Key\":\"2207D3FF71CA0900CB22F4FF\",\"Value\":1},{\"Key\":\"ACF7D2FF1CCC0900FAFDF3FF\",\"Value\":1},{\"Key\":\"E7F2D2FFC6D7090027C3F3FF\",\"Value\":1},{\"Key\":\"A3FBD2FFDFD40900ECD0F3FF\",\"Value\":1},{\"Key\":\"28AAD2FF0EDF0900A78CF3FF\",\"Value\":1},{\"Key\":\"3CABD2FF03D209004DC3F3FF\",\"Value\":1},{\"Key\":\"0EEFD2FFE4C80900CF3BF4FF\",\"Value\":1},{\"Key\":\"04E1D2FF39C809001C3CF4FF\",\"Value\":1},{\"Key\":\"65B3D3FF2CE509007115F3FF\",\"Value\":1},{\"Key\":\"3E8DD3FF2CE50900DF28F3FF\",\"Value\":3},{\"Key\":\"05B0D2FF5FC709004110F4FF\",\"Value\":1},{\"Key\":\"E4BED2FFFFC70900C20FF4FF\",\"Value\":1},{\"Key\":\"019CD2FFDDC00900AF22F4FF\",\"Value\":1},{\"Key\":\"B866D2FF7CBE0900A861F4FF\",\"Value\":1},{\"Key\":\"A784D2FFDBBC0900134EF4FF\",\"Value\":1},{\"Key\":\"C777D2FF60BC09007C4BF4FF\",\"Value\":1},{\"Key\":\"62B0D2FFFFC10900015DF4FF\",\"Value\":1},{\"Key\":\"0E14D3FFD0C8090038B4F4FF\",\"Value\":1},{\"Key\":\"4D84D2FF3EBD09008D5DF4FF\",\"Value\":1},{\"Key\":\"34CBD2FF3AC309008CE1F4FF\",\"Value\":1},{\"Key\":\"5C12D3FF2AC8090013CFF4FF\",\"Value\":1},{\"Key\":\"FA87D2FF95BD09009475F4FF\",\"Value\":1},{\"Key\":\"E170D2FF49BE0900E871F4FF\",\"Value\":1},{\"Key\":\"D597D2FFC0BE09004861F4FF\",\"Value\":1},{\"Key\":\"1A80D2FF91BB09000E34F4FF\",\"Value\":1},{\"Key\":\"53D5D2FF4CC309009FFEF4FF\",\"Value\":1},{\"Key\":\"B3F2D2FF35C7090075B8F4FF\",\"Value\":1},{\"Key\":\"EC8AD3FF2CE50900BD4AF3FF\",\"Value\":3},{\"Key\":\"B674D2FFD2DD09007E84F3FF\",\"Value\":1},{\"Key\":\"BFD4D3FFA3F50900FF45F3FF\",\"Value\":3},{\"Key\":\"C913D2FF0AE309002560F3FF\",\"Value\":1},{\"Key\":\"76CDD1FFC8E309009151F3FF\",\"Value\":1},{\"Key\":\"CADED1FF08E309004E40F3FF\",\"Value\":1},{\"Key\":\"E5DED2FF1AE20900A891F3FF\",\"Value\":1},{\"Key\":\"62D7D2FFBEE009009D9CF3FF\",\"Value\":1},{\"Key\":\"93D5D2FF99BE09000F30F5FF\",\"Value\":1},{\"Key\":\"A0B2D2FF85C209001212F5FF\",\"Value\":1},{\"Key\":\"7ABCD2FF08C00900272FF5FF\",\"Value\":1},{\"Key\":\"1BCBD2FFFCC109004614F5FF\",\"Value\":1},{\"Key\":\"039AD2FF1CC10900CBCAF4FF\",\"Value\":1},{\"Key\":\"3338D3FFAAD909005AB6F3FF\",\"Value\":1},{\"Key\":\"E430D3FFCAE20900B27CF3FF\",\"Value\":1},{\"Key\":\"8823D3FF8ADD0900CA9FF3FF\",\"Value\":1},{\"Key\":\"0388D3FF79E30900B379F3FF\",\"Value\":1},{\"Key\":\"4882D3FF1CE20900C884F3FF\",\"Value\":1},{\"Key\":\"535ED3FF7ADB09005806F4FF\",\"Value\":1},{\"Key\":\"8671D3FF7ADB09008C0CF4FF\",\"Value\":1},{\"Key\":\"3576D3FF7ADB0900FC20F4FF\",\"Value\":1},{\"Key\":\"4168D3FF7ADB09002CBFF3FF\",\"Value\":1},{\"Key\":\"A96BD3FFA4E40900AA5FF3FF\",\"Value\":3},{\"Key\":\"185CD3FF8EE009007387F3FF\",\"Value\":3},{\"Key\":\"6EB1D3FF8FDA09000E7DF4FF\",\"Value\":1},{\"Key\":\"ED0AD3FFCACF09004FF0F3FF\",\"Value\":3},{\"Key\":\"82A3D3FF4BDA0900546EF4FF\",\"Value\":1},{\"Key\":\"B0F8D2FFF0C809002248F4FF\",\"Value\":1},{\"Key\":\"48F0D2FF39C809002F79F4FF\",\"Value\":1},{\"Key\":\"1EB2D3FFBED90900719CF4FF\",\"Value\":1},{\"Key\":\"278DD3FF2FDB09004954F4FF\",\"Value\":1},{\"Key\":\"DED9D2FF23C609005087F4FF\",\"Value\":1},{\"Key\":\"19C1D2FF68C40900A05BF4FF\",\"Value\":1},{\"Key\":\"33ADD2FFEFC00900B088F4FF\",\"Value\":1},{\"Key\":\"F1A0D2FF2ED80900E6A9F3FF\",\"Value\":3},{\"Key\":\"E28ED2FF4FC00900DCB7F4FF\",\"Value\":1},{\"Key\":\"E4A1D2FF31BF090015B1F4FF\",\"Value\":1},{\"Key\":\"FED6D2FF93C20900F00CF5FF\",\"Value\":1},{\"Key\":\"2B60D2FF10BE0900E93DF4FF\",\"Value\":1},{\"Key\":\"7B62D2FF40BE09003C4FF4FF\",\"Value\":1},{\"Key\":\"9FC9D3FFDCD709007D11F5FF\",\"Value\":1},{\"Key\":\"BDBFD3FFB5D909006AE5F4FF\",\"Value\":1},{\"Key\":\"D62DD4FFA8D209005AEAF5FF\",\"Value\":1},{\"Key\":\"03CED3FF3CD60900472EF5FF\",\"Value\":1},{\"Key\":\"CDBBD3FF82D50900522FF5FF\",\"Value\":1},{\"Key\":\"0CB1D3FF32D909008EAFF4FF\",\"Value\":1},{\"Key\":\"96B5D3FFC4E609006DE5F3FF\",\"Value\":1},{\"Key\":\"0E9DD3FF7ADB0900082FF4FF\",\"Value\":1},{\"Key\":\"3276D3FF7ADB09008C39F4FF\",\"Value\":1},{\"Key\":\"EB7FD3FF7ADB09001337F4FF\",\"Value\":1},{\"Key\":\"F38CD3FFE6D909007A61F4FF\",\"Value\":1},{\"Key\":\"2EF3D2FFBDC10900B21AF5FF\",\"Value\":1},{\"Key\":\"394FD3FF7ADB09000BBEF3FF\",\"Value\":1},{\"Key\":\"DE5BD2FFECBD09004B23F4FF\",\"Value\":1},{\"Key\":\"0DE6D2FF98CE090086E7F3FF\",\"Value\":3},{\"Key\":\"E13AD3FFC8DA09002ADBF3FF\",\"Value\":1},{\"Key\":\"4AD0D2FF59C909009A12F4FF\",\"Value\":1},{\"Key\":\"EB1FD3FF87CF0900870AF4FF\",\"Value\":1},{\"Key\":\"0FACD3FF2CE809000592F3FF\",\"Value\":3},{\"Key\":\"8EBAD3FFAEE609008AEFF3FF\",\"Value\":1},{\"Key\":\"0880D2FFDAC80900E1D1F3FF\",\"Value\":3},{\"Key\":\"6853D2FF25D609008DB0F3FF\",\"Value\":3},{\"Key\":\"D40FD2FF64E20900B96EF3FF\",\"Value\":3},{\"Key\":\"FD14D2FF43C30900D52EF4FF\",\"Value\":1},{\"Key\":\"162BD2FF38C20900183CF4FF\",\"Value\":1},{\"Key\":\"1A42D2FFE8C009008019F4FF\",\"Value\":1},{\"Key\":\"4700D2FFE8DF09004190F3FF\",\"Value\":1},{\"Key\":\"1AF2D1FFAADE09004B9FF3FF\",\"Value\":1},{\"Key\":\"72CDD1FF61E309002D3EF3FF\",\"Value\":1},{\"Key\":\"EEB5D1FFB3E30900CBD6F2FF\",\"Value\":3},{\"Key\":\"1AC7D1FF2CE509007004F3FF\",\"Value\":1},{\"Key\":\"0AB2D1FF2CE509007AF4F2FF\",\"Value\":1},{\"Key\":\"3ED6D1FFBDE209008829F3FF\",\"Value\":3},{\"Key\":\"BDB3D1FFFEE40900BA30F3FF\",\"Value\":1},{\"Key\":\"BC97D1FFD9E20900F0CBF2FF\",\"Value\":1},{\"Key\":\"EA86D1FFD2E10900BCBEF2FF\",\"Value\":1},{\"Key\":\"3275D1FFFCE3090039CEF2FF\",\"Value\":3},{\"Key\":\"CF92D1FF2CE50900BFF4F2FF\",\"Value\":1},{\"Key\":\"B958D1FFF6DC0900949EF2FF\",\"Value\":3},{\"Key\":\"A89FD1FF2CE5090096F6F2FF\",\"Value\":1},{\"Key\":\"EEB8D1FF6EE10900A2BAF2FF\",\"Value\":1},{\"Key\":\"4EEED1FF07E309002A58F3FF\",\"Value\":1},{\"Key\":\"CF32D2FF2BCE090065DBF3FF\",\"Value\":1},{\"Key\":\"D5ECD1FF62E009000B90F3FF\",\"Value\":1},{\"Key\":\"8D06D2FF62C409005E7DF4FF\",\"Value\":1},{\"Key\":\"5451D2FFA1C90900F0DAF3FF\",\"Value\":1},{\"Key\":\"F2F9D1FF72C409009154F4FF\",\"Value\":1},{\"Key\":\"051CD2FF2EC409003055F4FF\",\"Value\":1},{\"Key\":\"8A06D2FF6EC40900AF69F4FF\",\"Value\":1},{\"Key\":\"0B49D2FFDFC00900E746F4FF\",\"Value\":1},{\"Key\":\"4112D2FF4FC40900344EF4FF\",\"Value\":1},{\"Key\":\"C112D2FF42C209004DC3F4FF\",\"Value\":1},{\"Key\":\"2605D2FFA9C20900E2ABF4FF\",\"Value\":1},{\"Key\":\"98D4D1FFB5BD090095ACF4FF\",\"Value\":1},{\"Key\":\"6E74D2FF06BF0900B588F4FF\",\"Value\":1},{\"Key\":\"2304D2FF23C1090066C3F4FF\",\"Value\":1},{\"Key\":\"E9C8D1FF4BB009005800F5FF\",\"Value\":1},{\"Key\":\"27D1D1FF14B909008ED0F4FF\",\"Value\":1},{\"Key\":\"DAE4D1FFC6BE090078B8F4FF\",\"Value\":1},{\"Key\":\"431FD2FF64C409000769F4FF\",\"Value\":1},{\"Key\":\"302CD2FFD4C209000048F4FF\",\"Value\":1},{\"Key\":\"AA5BD2FF74C4090077DCF4FF\",\"Value\":1},{\"Key\":\"4F35D2FFE0C30900AE85F4FF\",\"Value\":1},{\"Key\":\"643AD2FF4AC30900C06EF4FF\",\"Value\":1},{\"Key\":\"144DD2FF82C10900BB6DF4FF\",\"Value\":1},{\"Key\":\"5C48D2FF8FC209009687F4FF\",\"Value\":1},{\"Key\":\"AD35D2FFF8C30900C292F4FF\",\"Value\":1},{\"Key\":\"D84DD2FFDAD10900F3C2F3FF\",\"Value\":1},{\"Key\":\"0E69D2FF0EDD0900E989F3FF\",\"Value\":1},{\"Key\":\"DBC6D1FF25B40900F9E4F4FF\",\"Value\":1},{\"Key\":\"23DFD1FFFAC109002582F4FF\",\"Value\":1},{\"Key\":\"ADEDD1FF45C209000B95F4FF\",\"Value\":1},{\"Key\":\"EDE0D1FF01C30900A26CF4FF\",\"Value\":1},{\"Key\":\"C1C7D1FF3DC109009D62F4FF\",\"Value\":1},{\"Key\":\"FFBAD1FF1CBF0900CF6CF4FF\",\"Value\":1},{\"Key\":\"A4CBD1FF71BF09003687F4FF\",\"Value\":1},{\"Key\":\"F3BCD1FF32BE0900647DF4FF\",\"Value\":1},{\"Key\":\"DFCAD1FFA1BD0900749FF4FF\",\"Value\":1},{\"Key\":\"D3B5D1FF89BB09008390F4FF\",\"Value\":1},{\"Key\":\"0A0AD3FF1BE509002252F3FF\",\"Value\":1},{\"Key\":\"9364D3FF7ADB090079EEF3FF\",\"Value\":3},{\"Key\":\"6E7ED1FF2CE5090034FCF2FF\",\"Value\":1},{\"Key\":\"AA80D1FF2CE50900202FF3FF\",\"Value\":1},{\"Key\":\"987FD1FF2CE50900B23AF3FF\",\"Value\":1},{\"Key\":\"3450D1FF2CE509006D2FF3FF\",\"Value\":1},{\"Key\":\"9B9DD1FF2CE509006014F3FF\",\"Value\":3},{\"Key\":\"01A3D1FF2CE509002A31F3FF\",\"Value\":1},{\"Key\":\"DE9AD1FF2CE509005848F3FF\",\"Value\":1},{\"Key\":\"A5D8D1FF32E30900D469F3FF\",\"Value\":3},{\"Key\":\"9F74D1FFC1E40900A35FF3FF\",\"Value\":3},{\"Key\":\"F765D1FFC0E40900D36CF3FF\",\"Value\":1},{\"Key\":\"A642D1FF2CE50900C140F3FF\",\"Value\":1},{\"Key\":\"8336D1FF2CE50900DA52F3FF\",\"Value\":1},{\"Key\":\"6452D1FF2CE50900256AF3FF\",\"Value\":1},{\"Key\":\"2E58D1FF2CE50900FB46F3FF\",\"Value\":1},{\"Key\":\"6337D1FFFDE409006B83F3FF\",\"Value\":1},{\"Key\":\"FB3FD1FF2BE50900C37BF3FF\",\"Value\":1},{\"Key\":\"F838D1FF2CE509004F6AF3FF\",\"Value\":1},{\"Key\":\"6D06D3FFC5C809001B94F4FF\",\"Value\":1},{\"Key\":\"17E1D2FF4BC60900309EF4FF\",\"Value\":1},{\"Key\":\"E5BED2FFFAC309002B6FF4FF\",\"Value\":1},{\"Key\":\"0137D3FFD6D509006D08F4FF\",\"Value\":1},{\"Key\":\"B52BD3FFC1CF09007022F4FF\",\"Value\":1},{\"Key\":\"5842D3FFC3D109002A48F4FF\",\"Value\":1},{\"Key\":\"8D20D3FFC3CA0900B348F4FF\",\"Value\":1},{\"Key\":\"9736D3FFC1CA0900B997F4FF\",\"Value\":1},{\"Key\":\"3F4FD3FFAFD40900194CF4FF\",\"Value\":1},{\"Key\":\"5236D3FFEFCC09005066F4FF\",\"Value\":1},{\"Key\":\"166CD3FF1ED0090032C2F4FF\",\"Value\":1},{\"Key\":\"985AD3FF6ACD09003FBBF4FF\",\"Value\":1},{\"Key\":\"2D5CD3FF4CD30900BB6CF4FF\",\"Value\":1},{\"Key\":\"6AEFD2FF19E50900505FF3FF\",\"Value\":1},{\"Key\":\"0407D2FF4ADB09001FB0F3FF\",\"Value\":3},{\"Key\":\"80D3D1FFA9DD09002CAFF3FF\",\"Value\":3},{\"Key\":\"6FAFD1FFB1E109000F9EF3FF\",\"Value\":1},{\"Key\":\"BE9AD1FFFEE1090073AAF3FF\",\"Value\":1},{\"Key\":\"2099D1FF30E10900B4B4F3FF\",\"Value\":1},{\"Key\":\"92BAD1FF4DD2090042EBF3FF\",\"Value\":3},{\"Key\":\"3EC6D1FF75D70900B4D3F3FF\",\"Value\":1},{\"Key\":\"8B95D1FF93DA0900A2D1F3FF\",\"Value\":1},{\"Key\":\"24DFD1FF57CF0900D3ECF3FF\",\"Value\":1},{\"Key\":\"8EEED1FF7CCF09001BE9F3FF\",\"Value\":1},{\"Key\":\"2B04D2FF0ECC090026EFF3FF\",\"Value\":1},{\"Key\":\"6802D2FFF4C509001403F4FF\",\"Value\":1},{\"Key\":\"4CECD1FF97C809001902F4FF\",\"Value\":1},{\"Key\":\"F1DDD1FF0ACB090006FDF3FF\",\"Value\":1},{\"Key\":\"A421D2FFF4CD090031E2F3FF\",\"Value\":3},{\"Key\":\"F5CBD1FF5FCB09008200F4FF\",\"Value\":1},{\"Key\":\"6518D2FF70C10900E012F4FF\",\"Value\":1},{\"Key\":\"9F11D2FF0BC309009A22F4FF\",\"Value\":1},{\"Key\":\"2CF8D1FF10C50900ED22F4FF\",\"Value\":1},{\"Key\":\"18D9D1FFBCC609006B10F4FF\",\"Value\":1},{\"Key\":\"32C7D1FF7DC709008F0FF4FF\",\"Value\":1},{\"Key\":\"0BB3D1FF15C709002E15F4FF\",\"Value\":1},{\"Key\":\"DAC9D1FF2BC509000E29F4FF\",\"Value\":1},{\"Key\":\"69FFD1FF1ED3090003D7F3FF\",\"Value\":1},{\"Key\":\"09B3D1FFF3C409006223F4FF\",\"Value\":1},{\"Key\":\"9BB5D1FF6BC20900603CF4FF\",\"Value\":1},{\"Key\":\"A4A1D1FF44C309003329F4FF\",\"Value\":1},{\"Key\":\"F39BD1FFEDBB0900805FF4FF\",\"Value\":1},{\"Key\":\"561DD3FF2CE50900F242F3FF\",\"Value\":1},{\"Key\":\"D170D3FF7ADB0900ABDBF3FF\",\"Value\":1},{\"Key\":\"F188D3FF7ADB0900FCEAF3FF\",\"Value\":3},{\"Key\":\"E6A3D3FFC4DC0900D60DF4FF\",\"Value\":3},{\"Key\":\"BD56D1FF06E4090006C8F2FF\",\"Value\":3},{\"Key\":\"4B39D1FF2CE5090057E6F2FF\",\"Value\":1},{\"Key\":\"234ED1FF2CE509007AE4F2FF\",\"Value\":1},{\"Key\":\"182AD1FF25E5090016DEF2FF\",\"Value\":1},{\"Key\":\"124CD1FF2CE509007103F3FF\",\"Value\":3},{\"Key\":\"5F39D1FF2CE50900E4FEF2FF\",\"Value\":1},{\"Key\":\"0CB2D1FF08E509009640F3FF\",\"Value\":1},{\"Key\":\"F584D2FF3ED809008E7FF2FF\",\"Value\":1},{\"Key\":\"0986D2FFFAD809001872F2FF\",\"Value\":1},{\"Key\":\"9A13D2FF1EE5090033DEF2FF\",\"Value\":1},{\"Key\":\"ABCBD3FF6CE409006912F4FF\",\"Value\":3},{\"Key\":\"EAE9D3FF8EF3090077EDF3FF\",\"Value\":3},{\"Key\":\"A326D4FF0E040A0015F1F3FF\",\"Value\":3},{\"Key\":\"784DD4FFAD190A00B1D3F3FF\",\"Value\":3},{\"Key\":\"2184D3FFCBE209002DFEF2FF\",\"Value\":1},{\"Key\":\"305BD4FF3A060A009B0BF4FF\",\"Value\":3},{\"Key\":\"7BC5D2FF86C609000330F4FF\",\"Value\":3},{\"Key\":\"B300D3FF31C90900415EF4FF\",\"Value\":3},{\"Key\":\"12A3D2FF12C009004B6DF4FF\",\"Value\":3},{\"Key\":\"502DD3FF7ECB09000E68F4FF\",\"Value\":1},{\"Key\":\"BB58D3FF7ADB09008EDBF3FF\",\"Value\":1},{\"Key\":\"EA23C8FFADDA0500AA1B5800\",\"Value\":1},{\"Key\":\"87EED3FF20090A00B82DF3FF\",\"Value\":1},{\"Key\":\"79F5D3FFFD0D0A00941AF3FF\",\"Value\":1},{\"Key\":\"A602D4FFA4160A00442BF3FF\",\"Value\":1},{\"Key\":\"6812D3FF9CC90900E46CF4FF\",\"Value\":1},{\"Key\":\"1A1ED3FF86C909006382F4FF\",\"Value\":1},{\"Key\":\"3E52D2FF38C00900D8F2F3FF\",\"Value\":3},{\"Key\":\"503ED2FF12C209008C55F4FF\",\"Value\":3},{\"Key\":\"987BD6FF6C7F04009CB55B00\",\"Value\":1},{\"Key\":\"1962D6FF507B040039A75B00\",\"Value\":1},{\"Key\":\"2D5ED6FF0B5804009E7D5B00\",\"Value\":1},{\"Key\":\"B0ACD6FFF8460400252D5B00\",\"Value\":1},{\"Key\":\"3F9DD6FF194A0400A6335B00\",\"Value\":1},{\"Key\":\"7775D6FF3865040069945B00\",\"Value\":1},{\"Key\":\"9CF2D8FFD44305003D013400\",\"Value\":1},{\"Key\":\"3764D8FF12620500F30F3100\",\"Value\":1},{\"Key\":\"7B66D8FF996205009FFE3000\",\"Value\":1},{\"Key\":\"84F2D2FFFFBE0500271E3000\",\"Value\":1},{\"Key\":\"0AF9D2FFD6BE050097313000\",\"Value\":1},{\"Key\":\"CC06D3FF54BE0500DE4A3000\",\"Value\":1},{\"Key\":\"EF13D3FF22BC0500B3DB2F00\",\"Value\":1},{\"Key\":\"B147D3FF45BB0500D45D2F00\",\"Value\":1},{\"Key\":\"F148D3FFE7B90500226F2F00\",\"Value\":1},{\"Key\":\"E92DD3FFB9BB05005D8A2F00\",\"Value\":1},{\"Key\":\"9C23D3FF73BC0500E2942F00\",\"Value\":1},{\"Key\":\"1C31D3FF1DB9050014CD2F00\",\"Value\":1},{\"Key\":\"1F20D3FFA6BA05005EE72F00\",\"Value\":1},{\"Key\":\"0E47D3FFCEB50500E8E42F00\",\"Value\":1},{\"Key\":\"C61ED3FF5FBA050092073000\",\"Value\":1},{\"Key\":\"2C33D3FF50B8050037123000\",\"Value\":1},{\"Key\":\"334BD3FF8BB50500521C3000\",\"Value\":1},{\"Key\":\"64DED2FFC9C005008F073000\",\"Value\":1},{\"Key\":\"8EF3D2FFC3BE0500E1123000\",\"Value\":1},{\"Key\":\"7906D3FFD3BC05004F0B3000\",\"Value\":1},{\"Key\":\"661FE1FFCBCF07006AB41C00\",\"Value\":1},{\"Key\":\"7239E1FFC7D1070074B61C00\",\"Value\":1},{\"Key\":\"54F3B4FF3EA708003D4BEFFF\",\"Value\":1},{\"Key\":\"35E3B4FFDFA60800C356EFFF\",\"Value\":1},{\"Key\":\"73A0B4FF97D10800B2C5EEFF\",\"Value\":1},{\"Key\":\"8AC6B4FF29BA08002929EFFF\",\"Value\":1},{\"Key\":\"97BDB4FF21B60800BA35EFFF\",\"Value\":1},{\"Key\":\"015AB4FFDBA308002972EFFF\",\"Value\":1},{\"Key\":\"375AB4FF949B0800699AEFFF\",\"Value\":1},{\"Key\":\"8241B4FFAD9E0800AC82EFFF\",\"Value\":1},{\"Key\":\"F242B4FFF8990800D397EFFF\",\"Value\":1},{\"Key\":\"D043B4FFADA308000F71EFFF\",\"Value\":1},{\"Key\":\"5729B4FFF29C0800A186EFFF\",\"Value\":1},{\"Key\":\"F334B4FF1CF40800EA25EEFF\",\"Value\":1},{\"Key\":\"9612B4FF3DEF0800F726EEFF\",\"Value\":1},{\"Key\":\"CC12B4FFD8F708003A0EEEFF\",\"Value\":1},{\"Key\":\"FD7DB3FFF6F508006A4AEDFF\",\"Value\":1},{\"Key\":\"8D71B3FF5DEE0800F05AEDFF\",\"Value\":1},{\"Key\":\"34A2B7FF617908009E40F0FF\",\"Value\":1},{\"Key\":\"AFEFD0FF2CE50900ECD6F2FF\",\"Value\":3},{\"Key\":\"27D6D0FF2CE5090075DDF2FF\",\"Value\":3},{\"Key\":\"64D4D0FF2CE50900B3F0F2FF\",\"Value\":1},{\"Key\":\"9F1ED1FF2CE509001CFEF2FF\",\"Value\":1},{\"Key\":\"5E0FD1FF2CE5090021E4F2FF\",\"Value\":1},{\"Key\":\"D20CD1FF1FE50900ADCCF2FF\",\"Value\":1},{\"Key\":\"AF1CD1FF2CE509002F15F3FF\",\"Value\":1},{\"Key\":\"ECA6D0FF2CE50900C6CDF2FF\",\"Value\":1},{\"Key\":\"6CABD0FF2CE509008CBEF2FF\",\"Value\":1},{\"Key\":\"BD9AD0FF2CE509006CCEF2FF\",\"Value\":1},{\"Key\":\"9395D0FF2CE5090046BEF2FF\",\"Value\":1},{\"Key\":\"20BBD0FF2CE50900D6BDF2FF\",\"Value\":1},{\"Key\":\"1AF0D0FF2CE509000608F3FF\",\"Value\":1},{\"Key\":\"BC72D0FF2CE50900D2C5F2FF\",\"Value\":3},{\"Key\":\"3387D0FF2CE50900F8BCF2FF\",\"Value\":1},{\"Key\":\"A68BD0FFF3E409006363F2FF\",\"Value\":1},{\"Key\":\"47E5D0FF2CE5090034B8F2FF\",\"Value\":1},{\"Key\":\"1FF4D0FF2CE50900E6B8F2FF\",\"Value\":1},{\"Key\":\"6806D1FFF5E409005EBAF2FF\",\"Value\":1},{\"Key\":\"F7A6D0FF2CE509004F94F2FF\",\"Value\":1},{\"Key\":\"6094D0FF2CE509001480F2FF\",\"Value\":1},{\"Key\":\"12BBD0FF2CE509009FA5F2FF\",\"Value\":1},{\"Key\":\"B5CFD0FF2CE509008AABF2FF\",\"Value\":1},{\"Key\":\"B8CFD0FF2CE50900DDB7F2FF\",\"Value\":1},{\"Key\":\"771DD1FF0EE50900F546F3FF\",\"Value\":1},{\"Key\":\"6320D1FF2CE50900EF60F3FF\",\"Value\":1},{\"Key\":\"0BB9D0FF2CE509000F05F3FF\",\"Value\":3},{\"Key\":\"DCC2D0FF2CE509008DFEF2FF\",\"Value\":1},{\"Key\":\"80ACD0FF2CE50900C4F1F2FF\",\"Value\":1},{\"Key\":\"7DCED0FF2CE50900D817F3FF\",\"Value\":1},{\"Key\":\"6353D1FFEBE40900E777F3FF\",\"Value\":1},{\"Key\":\"0F08D1FF2CE509008E2CF3FF\",\"Value\":3},{\"Key\":\"E6D8D0FF2CE50900F207F3FF\",\"Value\":1},{\"Key\":\"901ED1FF01E50900252FF3FF\",\"Value\":1},{\"Key\":\"F9CFD0FF2CE509002C31F3FF\",\"Value\":1},{\"Key\":\"11C4D0FF2CE509009747F3FF\",\"Value\":1},{\"Key\":\"EBBDD0FF2CE509002E31F3FF\",\"Value\":1},{\"Key\":\"A3D7D0FF2CE509009048F3FF\",\"Value\":1},{\"Key\":\"1FEBD0FF2CE50900F43BF3FF\",\"Value\":1},{\"Key\":\"8EDED0FF2CE50900742DF3FF\",\"Value\":1},{\"Key\":\"DBD3D0FF2CE509003A53F3FF\",\"Value\":1},{\"Key\":\"AA69D1FF1DE40900B789F3FF\",\"Value\":1},{\"Key\":\"0166D1FFECC009008618F4FF\",\"Value\":1},{\"Key\":\"467FD1FFEEDD090023C8F3FF\",\"Value\":1},{\"Key\":\"2442D1FF1FE509000F2BF3FF\",\"Value\":1},{\"Key\":\"9132D1FF2CE50900EC1CF3FF\",\"Value\":1},{\"Key\":\"CBF3D0FF82D70900AC4AF2FF\",\"Value\":1},{\"Key\":\"84A5D1FF0CC109007E3AF4FF\",\"Value\":1},{\"Key\":\"D980D1FFBBB009006191F4FF\",\"Value\":1},{\"Key\":\"EBB5D3FF2CE509009105F3FF\",\"Value\":1},{\"Key\":\"38CFD3FF79E70900CB06F3FF\",\"Value\":1},{\"Key\":\"531BD1FF2CE509006975F3FF\",\"Value\":1},{\"Key\":\"E605D1FF2CE50900E06EF3FF\",\"Value\":1},{\"Key\":\"9E0ED1FF2CE509007C5FF3FF\",\"Value\":1},{\"Key\":\"BA3FD1FF2BE309000EA9F3FF\",\"Value\":1},{\"Key\":\"7140D1FFDCE30900E99DF3FF\",\"Value\":1},{\"Key\":\"C730D1FF16E40900DF9CF3FF\",\"Value\":1},{\"Key\":\"7923D1FFB7E409002792F3FF\",\"Value\":1},{\"Key\":\"C6EBD0FF2CE509004E6CF3FF\",\"Value\":1},{\"Key\":\"8C5BD1FFCAE30900B498F3FF\",\"Value\":3},{\"Key\":\"2D65D1FF06E2090089B7F3FF\",\"Value\":1},{\"Key\":\"7833D1FF94DE09006FD1F3FF\",\"Value\":1},{\"Key\":\"062DD1FF21E309006DB1F3FF\",\"Value\":1},{\"Key\":\"C31AD1FFB2E3090019B6F3FF\",\"Value\":1},{\"Key\":\"1E15D1FF18E50900D68EF3FF\",\"Value\":3},{\"Key\":\"19FAD0FF2CE509007279F3FF\",\"Value\":1},{\"Key\":\"DDF3D0FFFBE509002E8FF3FF\",\"Value\":1},{\"Key\":\"62BAD0FF2CE50900521CF3FF\",\"Value\":1},{\"Key\":\"99A7D0FF2CE50900C61CF3FF\",\"Value\":1},{\"Key\":\"1D96D0FF2CE50900C5F7F2FF\",\"Value\":1},{\"Key\":\"FC82D0FF2CE5090027DEF2FF\",\"Value\":1},{\"Key\":\"6C86D0FF2CE50900FCD0F2FF\",\"Value\":1},{\"Key\":\"6674D0FF2CE5090051E0F2FF\",\"Value\":1},{\"Key\":\"BE60D0FF2CE5090041DFF2FF\",\"Value\":1},{\"Key\":\"7E5FD0FF1EE5090079D1F2FF\",\"Value\":1},{\"Key\":\"7761D0FF8EE30900ACBBF2FF\",\"Value\":1},{\"Key\":\"BB4DD0FFD6E309002EB9F2FF\",\"Value\":1},{\"Key\":\"71AAD0FF3AE509003631F3FF\",\"Value\":1},{\"Key\":\"0BA1D0FFADE509009E3CF3FF\",\"Value\":1},{\"Key\":\"898AD0FF5FE60900A22EF3FF\",\"Value\":1},{\"Key\":\"AC61D0FF2CE5090020FEF2FF\",\"Value\":1},{\"Key\":\"8A74D0FF2CE50900FCF4F2FF\",\"Value\":1},{\"Key\":\"8045D0FF9FE5090008FFF2FF\",\"Value\":1},{\"Key\":\"2E53D0FF1BE609005914F3FF\",\"Value\":3},{\"Key\":\"4C3FD0FF3AE909008523F3FF\",\"Value\":1},{\"Key\":\"7D59D0FF70E80900A62EF3FF\",\"Value\":1},{\"Key\":\"1D71D0FF6BE609001E26F3FF\",\"Value\":3},{\"Key\":\"BA88D0FF40E809005A45F3FF\",\"Value\":1},{\"Key\":\"96F4D0FF2CE509003B21F3FF\",\"Value\":1},{\"Key\":\"7A19D0FFC4E6090019CCF2FF\",\"Value\":1},{\"Key\":\"C229D0FF19E60900D5D1F2FF\",\"Value\":3},{\"Key\":\"EC1AD0FF0FE809005CDAF2FF\",\"Value\":1},{\"Key\":\"464DD0FF2CE509000FDEF2FF\",\"Value\":1},{\"Key\":\"6881D0FF2CE509006AF2F2FF\",\"Value\":1},{\"Key\":\"AA37D0FFAFE309008BA7F2FF\",\"Value\":3},{\"Key\":\"A60FD0FF96E50900CEB3F2FF\",\"Value\":1},{\"Key\":\"E994D0FF2CE50900DCDEF2FF\",\"Value\":1},{\"Key\":\"55A8D0FF2CE509003CE4F2FF\",\"Value\":1},{\"Key\":\"A15AD0FF36E40900ECA8F2FF\",\"Value\":1},{\"Key\":\"7C92D1FFFBD1090016EBF3FF\",\"Value\":1},{\"Key\":\"8E99D1FF67B40900579FF4FF\",\"Value\":1},{\"Key\":\"F649D0FFC8ED09004948F3FF\",\"Value\":3},{\"Key\":\"D40DD0FF17EF09007D23F3FF\",\"Value\":3},{\"Key\":\"AEDFCFFFDBEF0900DB08F3FF\",\"Value\":1},{\"Key\":\"ADDECFFFBCEE09007BFDF2FF\",\"Value\":1},{\"Key\":\"EDB3CFFF55F109001E08F3FF\",\"Value\":1},{\"Key\":\"57AFCFFFB7F20900851CF3FF\",\"Value\":1},{\"Key\":\"4230D0FF05EB09003521F3FF\",\"Value\":1},{\"Key\":\"5994CFFFB0F309006815F3FF\",\"Value\":1},{\"Key\":\"5C2AD0FFE9E809006208F3FF\",\"Value\":1},{\"Key\":\"129CCFFF77F40900BE2FF3FF\",\"Value\":1},{\"Key\":\"FCB0CFFF5DF30900FE2FF3FF\",\"Value\":1},{\"Key\":\"28CCCFFFE3F00900BD0CF3FF\",\"Value\":1},{\"Key\":\"22ECCFFF8AE709004FC8F2FF\",\"Value\":1},{\"Key\":\"BF27D0FF20E809000BFDF2FF\",\"Value\":1},{\"Key\":\"0E99D0FF2CE5090030A5F2FF\",\"Value\":1},{\"Key\":\"45E4D0FF06E5090092ABF2FF\",\"Value\":1},{\"Key\":\"27FAD0FF7DE4090004A8F2FF\",\"Value\":1},{\"Key\":\"5696D0FF2CE50900BB91F2FF\",\"Value\":1},{\"Key\":\"955DD0FFF3E409004D45F2FF\",\"Value\":1},{\"Key\":\"81FECFFF70E509008DA8F2FF\",\"Value\":3},{\"Key\":\"FC86CFFF15ED090066CBF2FF\",\"Value\":1},{\"Key\":\"F291CFFFCAEE09003FDFF2FF\",\"Value\":1},{\"Key\":\"E079CFFF1CEF0900F8DBF2FF\",\"Value\":1},{\"Key\":\"86A9CFFF0DEB0900F9C8F2FF\",\"Value\":1},{\"Key\":\"28ABCFFFE9ED0900E6E1F2FF\",\"Value\":1},{\"Key\":\"DBC0D0FF2CE5090001E2F2FF\",\"Value\":1},{\"Key\":\"A045D0FF18E50900C73DF2FF\",\"Value\":3},{\"Key\":\"24EBCFFF2CE509007145F2FF\",\"Value\":3},{\"Key\":\"6F4DD0FF2CE509003E5EF2FF\",\"Value\":1},{\"Key\":\"7BACD0FF2CE50900E8AAF2FF\",\"Value\":1},{\"Key\":\"D4BCD0FF6CE60900696AF3FF\",\"Value\":1},{\"Key\":\"91BAD0FFD8E909001C8FF3FF\",\"Value\":1},{\"Key\":\"E2D3D0FFDAE60900ED7AF3FF\",\"Value\":1},{\"Key\":\"F36BD0FFAEEC09007755F3FF\",\"Value\":3},{\"Key\":\"F374D0FFDDEF0900C882F3FF\",\"Value\":1},{\"Key\":\"F54FD0FF56F309005690F3FF\",\"Value\":1},{\"Key\":\"7340D0FF2CF7090086B5F3FF\",\"Value\":1},{\"Key\":\"3945D0FF99F50900C5AAF3FF\",\"Value\":1},{\"Key\":\"4511D0FF6BF709001E9EF3FF\",\"Value\":3},{\"Key\":\"EBEACFFFDFF30900A765F3FF\",\"Value\":3},{\"Key\":\"BC19D1FFD7E20900A1A6F2FF\",\"Value\":1},{\"Key\":\"9925D1FF189B0900DD86F4FF\",\"Value\":1},{\"Key\":\"5434D1FF609D0900FF93F4FF\",\"Value\":1},{\"Key\":\"001FD1FF939709009795F4FF\",\"Value\":1},{\"Key\":\"941CD1FF9D950900F1A7F4FF\",\"Value\":1},{\"Key\":\"663BD1FFC59C09000FA9F4FF\",\"Value\":1},{\"Key\":\"6109D1FF21900900DAAEF4FF\",\"Value\":1},{\"Key\":\"DB97D2FFE6C30900780DF5FF\",\"Value\":1},{\"Key\":\"D998D2FF73C3090027F6F4FF\",\"Value\":1},{\"Key\":\"C189D2FFECC3090028F5F4FF\",\"Value\":1},{\"Key\":\"AA39D3FF9AC9090003F4F4FF\",\"Value\":1},{\"Key\":\"B644D3FF18CA0900CCDDF4FF\",\"Value\":1},{\"Key\":\"B752D3FFECCB0900AFF3F4FF\",\"Value\":1},{\"Key\":\"ED74D3FF00D209001AB6F4FF\",\"Value\":1},{\"Key\":\"75EFD3FF18DC090043B6F4FF\",\"Value\":1},{\"Key\":\"C7EFD3FFDDDB090055C4F4FF\",\"Value\":1},{\"Key\":\"7FD8D3FF53DB0900539BF4FF\",\"Value\":1},{\"Key\":\"54E2D3FFCEDB0900889AF4FF\",\"Value\":1},{\"Key\":\"A0EED3FFB7DD0900F185F4FF\",\"Value\":1},{\"Key\":\"EBEED3FFF2DF09005361F4FF\",\"Value\":1},{\"Key\":\"93FBD3FF84E00900E77BF4FF\",\"Value\":1},{\"Key\":\"9B38D4FF6AEF0900DB48F4FF\",\"Value\":1},{\"Key\":\"393BD4FF52E6090066B1F4FF\",\"Value\":1},{\"Key\":\"9C22D4FFF9E20900A3AFF4FF\",\"Value\":1},{\"Key\":\"5F30D4FF5EE60900819FF4FF\",\"Value\":1},{\"Key\":\"3D3BD4FF55E4090039C9F4FF\",\"Value\":1},{\"Key\":\"5951D4FF0EE9090082B6F4FF\",\"Value\":1},{\"Key\":\"174CD4FFCAE5090032D1F4FF\",\"Value\":1},{\"Key\":\"6952D4FFC2EE09003184F4FF\",\"Value\":1},{\"Key\":\"C453D4FF49ED0900FB97F4FF\",\"Value\":1},{\"Key\":\"715DD4FF25F00900F894F4FF\",\"Value\":1},{\"Key\":\"022FD4FF3AE909005679F4FF\",\"Value\":1},{\"Key\":\"C434D4FF34EB0900F16EF4FF\",\"Value\":1},{\"Key\":\"7721D4FF2AE90900776BF4FF\",\"Value\":1},{\"Key\":\"DC5CD4FFD0F609005650F4FF\",\"Value\":1},{\"Key\":\"3344D4FFB3EE09006166F4FF\",\"Value\":1},{\"Key\":\"8251D4FFB8F409003449F4FF\",\"Value\":1},{\"Key\":\"4B6CD4FF4AF90900BF66F4FF\",\"Value\":1},{\"Key\":\"A869D4FF12F70900EA79F4FF\",\"Value\":1},{\"Key\":\"2482D4FFC9FB0900B185F4FF\",\"Value\":1},{\"Key\":\"9D81D4FFE3F60900A59EF4FF\",\"Value\":1},{\"Key\":\"578ED4FF1FF10900F7DEF4FF\",\"Value\":1},{\"Key\":\"D584D4FF84ED0900E0FAF4FF\",\"Value\":1},{\"Key\":\"118ED4FF1CF0090047F8F4FF\",\"Value\":1},{\"Key\":\"0991D4FF93EF0900A00CF5FF\",\"Value\":1},{\"Key\":\"5D81D4FFC1E909007E19F5FF\",\"Value\":1},{\"Key\":\"6A4ED4FF5DDE09001C24F5FF\",\"Value\":1},{\"Key\":\"B453D4FFCCE10900F111F5FF\",\"Value\":1},{\"Key\":\"FC5CD4FF3CE30900DB10F5FF\",\"Value\":1},{\"Key\":\"6A5FD4FF58E509006300F5FF\",\"Value\":1},{\"Key\":\"0883D4FF13F0090062C4F4FF\",\"Value\":1},{\"Key\":\"3582D4FFC6F10900B3B6F4FF\",\"Value\":1},{\"Key\":\"609DD4FF82F6090008C9F4FF\",\"Value\":1},{\"Key\":\"5ED7D4FF290C0A00E22BF5FF\",\"Value\":1},{\"Key\":\"04C8D4FF47020A003733F5FF\",\"Value\":1},{\"Key\":\"1BFED4FF3D240A00933FF5FF\",\"Value\":1},{\"Key\":\"3315D5FF2E2E0A007C25F5FF\",\"Value\":1},{\"Key\":\"F917D5FFB1300A002014F5FF\",\"Value\":1},{\"Key\":\"6230D5FFE6300A00DB45F5FF\",\"Value\":1},{\"Key\":\"CB3AD5FFA3330A005E48F5FF\",\"Value\":1},{\"Key\":\"3E58D5FFFA3A0A00F454F5FF\",\"Value\":1},{\"Key\":\"273CD5FFD9320A00BC56F5FF\",\"Value\":1},{\"Key\":\"FD57D5FFB9370A008B6DF5FF\",\"Value\":1},{\"Key\":\"0671D5FFE53A0A00F985F5FF\",\"Value\":1},{\"Key\":\"21ABD5FFBF590A00102AF5FF\",\"Value\":1},{\"Key\":\"95B4D5FF595D0A000C29F5FF\",\"Value\":1},{\"Key\":\"237AD5FFBF4E0A006FC8F4FF\",\"Value\":1},{\"Key\":\"3789D2FF09D80900CE5EF2FF\",\"Value\":1},{\"Key\":\"1997D2FF31D409007A5CF2FF\",\"Value\":1},{\"Key\":\"79BDE1FF89760C00FDE50200\",\"Value\":1},{\"Key\":\"7E83E3FF90AD1300330BECFF\",\"Value\":1},{\"Key\":\"6E9CE3FF79AE130003FEEBFF\",\"Value\":1},{\"Key\":\"7D9DE3FFCFAD1300090AECFF\",\"Value\":1},{\"Key\":\"CB9BE3FF5FB2130060DAEBFF\",\"Value\":1},{\"Key\":\"7F9ABCFFE3B2050028304E00\",\"Value\":1},{\"Key\":\"F086AEFF1FDE050030715600\",\"Value\":1},{\"Key\":\"1991AEFFBBDF05006D685600\",\"Value\":1},{\"Key\":\"9B99AEFF7CE505007B885600\",\"Value\":1},{\"Key\":\"C371AEFF1BD805002C465600\",\"Value\":1},{\"Key\":\"036AAEFF49D805001B6B5600\",\"Value\":1},{\"Key\":\"5657AEFF6FD6050050135600\",\"Value\":1},{\"Key\":\"5676AEFF8FD705003F2D5600\",\"Value\":1},{\"Key\":\"7C5CAEFF6FD60500A92B5600\",\"Value\":1},{\"Key\":\"7391AEFF9EDA05001A125600\",\"Value\":1},{\"Key\":\"B983AEFF6AD80500F2105600\",\"Value\":1},{\"Key\":\"6D49AEFF6FD6050023105600\",\"Value\":1},{\"Key\":\"1069AEFF72D60500A5F65500\",\"Value\":1},{\"Key\":\"497AAEFFB9D605000AF25500\",\"Value\":1},{\"Key\":\"1F85AEFFE1D60500D4E55500\",\"Value\":1},{\"Key\":\"DFAEAEFF62DC0500A8035600\",\"Value\":1},{\"Key\":\"3B97AEFF0DD90500F7F15500\",\"Value\":1},{\"Key\":\"DB90AEFF85D60500A4D95500\",\"Value\":1},{\"Key\":\"E492AEFFE0FB05008C4B5700\",\"Value\":1},{\"Key\":\"CF94AEFF53FE050055635700\",\"Value\":1},{\"Key\":\"11EAADFFF7D70500219E5600\",\"Value\":1},{\"Key\":\"F30FAEFF6FD60500CA5A5600\",\"Value\":1},{\"Key\":\"681FAEFF28DF050007BC5600\",\"Value\":1},{\"Key\":\"59D1ADFFB9DB05004DB25600\",\"Value\":1},{\"Key\":\"1FBBADFFAADB05007FBC5600\",\"Value\":1},{\"Key\":\"75ACADFF99D905008BAE5600\",\"Value\":1},{\"Key\":\"009FADFFF5D7050074AF5600\",\"Value\":1},{\"Key\":\"9882ADFF6FD3050088A05600\",\"Value\":1},{\"Key\":\"9C62E2FF463F050098CC2B00\",\"Value\":1},{\"Key\":\"6F55E2FFB73D0500E5B72B00\",\"Value\":1},{\"Key\":\"CDB7E2FF02460500C93E2C00\",\"Value\":1},{\"Key\":\"B982D3FF0D2B0800F6F9FFFF\",\"Value\":1},{\"Key\":\"8631D1FF32DD09002A98F2FF\",\"Value\":1},{\"Key\":\"77A6CFFF0FE80900BC9AF2FF\",\"Value\":1},{\"Key\":\"736CCFFFE7E90900D86AF2FF\",\"Value\":1},{\"Key\":\"6086CFFFC6E60900265EF2FF\",\"Value\":1},{\"Key\":\"1677CFFF0AEA09009F7EF2FF\",\"Value\":1},{\"Key\":\"A062CFFFB5EB09001A96F2FF\",\"Value\":1},{\"Key\":\"2C55CFFF9EEB09009176F2FF\",\"Value\":1},{\"Key\":\"0B50CFFF28EC09000784F2FF\",\"Value\":1},{\"Key\":\"74B0CFFF6FE409001253F2FF\",\"Value\":1},{\"Key\":\"C1A5CFFF74E409003656F2FF\",\"Value\":3},{\"Key\":\"22C4CFFFB0E40900145FF2FF\",\"Value\":1},{\"Key\":\"BC77CFFF0CE60900833CF2FF\",\"Value\":3},{\"Key\":\"A894CFFF8FE40900DF38F2FF\",\"Value\":1},{\"Key\":\"9989CFFF28E509005946F2FF\",\"Value\":1},{\"Key\":\"2C3ACFFF14F409006108F3FF\",\"Value\":1},{\"Key\":\"6348CFFF7BF1090038F6F2FF\",\"Value\":1},{\"Key\":\"E83ECFFFEEF10900FAF9F2FF\",\"Value\":1},{\"Key\":\"BFB5CFFF1CE509009535F2FF\",\"Value\":1},{\"Key\":\"40A0CFFFEAE40900B91EF2FF\",\"Value\":1},{\"Key\":\"19C7CFFF2CE509009625F2FF\",\"Value\":1},{\"Key\":\"A7C2CFFF2CE50900D737F2FF\",\"Value\":1},{\"Key\":\"9DD2CFFF2CE509008501F2FF\",\"Value\":1},{\"Key\":\"9FD2CFFF2CE5090033E9F1FF\",\"Value\":1},{\"Key\":\"4FD2CFFF2CE509008C15F2FF\",\"Value\":1},{\"Key\":\"25E9CFFFBAE4090019E4F1FF\",\"Value\":1},{\"Key\":\"93E4CFFFD8E3090015C9F1FF\",\"Value\":1},{\"Key\":\"10DECFFF10E2090081B2F1FF\",\"Value\":1},{\"Key\":\"1EF5CFFF92E009002CBCF1FF\",\"Value\":1},{\"Key\":\"B011D0FF69D709000BA7F1FF\",\"Value\":1},{\"Key\":\"2D1CD0FF58D709005AB7F1FF\",\"Value\":1},{\"Key\":\"C901D0FF95D80900D7A4F1FF\",\"Value\":1},{\"Key\":\"8F90CEFF5AF10900BE40F3FF\",\"Value\":1},{\"Key\":\"39CECEFFF9F309005725F3FF\",\"Value\":1},{\"Key\":\"D7C2CEFF3FF309002F23F3FF\",\"Value\":1},{\"Key\":\"A7CECEFF7DF50900FD3CF3FF\",\"Value\":1},{\"Key\":\"92C0CEFF21F40900EA39F3FF\",\"Value\":1},{\"Key\":\"67B8CEFF1FF30900B730F3FF\",\"Value\":1},{\"Key\":\"12F4CEFF17F80900EA3BF3FF\",\"Value\":1},{\"Key\":\"DB00CFFFF3F80900743BF3FF\",\"Value\":1},{\"Key\":\"F71CCFFFD0F509004717F3FF\",\"Value\":1},{\"Key\":\"9F6CCFFF39F409000409F3FF\",\"Value\":1},{\"Key\":\"DD60CFFF18F20900EDF6F2FF\",\"Value\":1},{\"Key\":\"E1B4CEFFD5F309000D45F3FF\",\"Value\":1},{\"Key\":\"38A4CEFFB7F20900E83EF3FF\",\"Value\":1},{\"Key\":\"BFA5CEFF3EF30900B750F3FF\",\"Value\":1},{\"Key\":\"1DB5CEFF87F409002F59F3FF\",\"Value\":1},{\"Key\":\"9EA7CEFFB5F30900C86AF3FF\",\"Value\":1},{\"Key\":\"92C0CEFF01F60900FC6AF3FF\",\"Value\":1},{\"Key\":\"C5D8CEFF44F80900D26AF3FF\",\"Value\":1},{\"Key\":\"8AF5CEFF1CF609004426F3FF\",\"Value\":1},{\"Key\":\"01E1CEFFEAF609006A3DF3FF\",\"Value\":1},{\"Key\":\"570CCFFF25F80900822DF3FF\",\"Value\":1},{\"Key\":\"D148CFFF90F509007C12F3FF\",\"Value\":1},{\"Key\":\"D386CFFF68F10900CBF1F2FF\",\"Value\":1},{\"Key\":\"6698CFFF67F0090085EFF2FF\",\"Value\":1},{\"Key\":\"E4DCCEFF87F50900DB2DF3FF\",\"Value\":1},{\"Key\":\"099FCEFFBCF10900FA2DF3FF\",\"Value\":1},{\"Key\":\"8C67CFFFD5ED090068D1F2FF\",\"Value\":1},{\"Key\":\"FF62CFFF5CEC090015BDF2FF\",\"Value\":1},{\"Key\":\"7688CFFF21F40900A512F3FF\",\"Value\":1},{\"Key\":\"9374D0FF2CE509002495F2FF\",\"Value\":1},{\"Key\":\"7987D0FF2CE509003196F2FF\",\"Value\":1},{\"Key\":\"F257CFFFD4EE090097DEF2FF\",\"Value\":1},{\"Key\":\"B1BBD0FF2CE5090055D1F2FF\",\"Value\":1},{\"Key\":\"DB66CEFFE8EC0900C704F3FF\",\"Value\":1},{\"Key\":\"9F78CEFFF2ED0900D2E8F2FF\",\"Value\":1},{\"Key\":\"903DCFFF5AF90900562DF3FF\",\"Value\":1},{\"Key\":\"6270CFFF8FF909001042F3FF\",\"Value\":1},{\"Key\":\"CF88CFFFA8F609000A3FF3FF\",\"Value\":1},{\"Key\":\"0B95CFFF4DF50900943AF3FF\",\"Value\":1},{\"Key\":\"2386CFFF0EF60900582EF3FF\",\"Value\":1},{\"Key\":\"2E6ECFFFE8F60900C022F3FF\",\"Value\":1},{\"Key\":\"77AACEFF6CF10900AA14F3FF\",\"Value\":1},{\"Key\":\"B789CFFF16F309000E05F3FF\",\"Value\":1},{\"Key\":\"C138CFFF04EA0900AC12F2FF\",\"Value\":1},{\"Key\":\"AB31CFFFBCEB09000524F2FF\",\"Value\":3},{\"Key\":\"B320CFFFF2EB0900C312F2FF\",\"Value\":1},{\"Key\":\"B323CFFFDDEA09002708F2FF\",\"Value\":1},{\"Key\":\"2D3ECFFF71E809001506F2FF\",\"Value\":1},{\"Key\":\"D1FFCEFFA4EE0900F12EF2FF\",\"Value\":1},{\"Key\":\"B7FECEFF29EE09005F1AF2FF\",\"Value\":1},{\"Key\":\"5AE6CEFF35EF0900731FF2FF\",\"Value\":1},{\"Key\":\"0057CFFFAAF80900052CF3FF\",\"Value\":1},{\"Key\":\"164FCFFF98FA09001539F3FF\",\"Value\":1},{\"Key\":\"4750CFFF02000A00B579F3FF\",\"Value\":1},{\"Key\":\"9469CEFF37EA0900763DF2FF\",\"Value\":3},{\"Key\":\"5841CEFF7AEB0900E249F2FF\",\"Value\":3},{\"Key\":\"E68ECEFF6DEC09003513F2FF\",\"Value\":1},{\"Key\":\"1BA1CEFF5AED09004F13F2FF\",\"Value\":1},{\"Key\":\"0C84CEFF9AEB09004033F2FF\",\"Value\":1},{\"Key\":\"B2D3CEFF3AEE09007A09F2FF\",\"Value\":1},{\"Key\":\"14B8CEFF0EEE09004514F2FF\",\"Value\":1},{\"Key\":\"B6C2CEFFF6EB090094EEF1FF\",\"Value\":1},{\"Key\":\"8B2BCEFFBFE60900EDF0F1FF\",\"Value\":1},{\"Key\":\"8B3ACEFF13E80900C1FEF1FF\",\"Value\":3},{\"Key\":\"8849CEFFA7E8090028ECF1FF\",\"Value\":1},{\"Key\":\"B93BCEFFB9E909001A16F2FF\",\"Value\":1},{\"Key\":\"9C87CEFF35EB0900EA44F2FF\",\"Value\":1},{\"Key\":\"F7D8CEFF96EF0900F42BF2FF\",\"Value\":1},{\"Key\":\"7B5ACEFF8AEA09005F58F2FF\",\"Value\":1},{\"Key\":\"38B8CEFFA9EE0900B32CF2FF\",\"Value\":1},{\"Key\":\"315ECEFFDAE909003F6EF2FF\",\"Value\":1},{\"Key\":\"7F39CFFFF7E40900D7BFF1FF\",\"Value\":1},{\"Key\":\"1C6ECEFFEBE9090082E3F1FF\",\"Value\":1},{\"Key\":\"868BCEFF72EB090023F1F1FF\",\"Value\":1},{\"Key\":\"72EBCEFF43EA0900F2E1F1FF\",\"Value\":1},{\"Key\":\"9278CEFFC0E8090003CBF1FF\",\"Value\":1},{\"Key\":\"4353CEFFFEE70900B0CEF1FF\",\"Value\":1},{\"Key\":\"9664CFFF2CE5090022CAF1FF\",\"Value\":1},{\"Key\":\"D702CFFF7DD809004E80F1FF\",\"Value\":1},{\"Key\":\"6144CEFFA6E7090050D8F1FF\",\"Value\":1},{\"Key\":\"533CCFFF01E60900B6E9F1FF\",\"Value\":1},{\"Key\":\"C992CFFFD6E309002B9CF1FF\",\"Value\":1},{\"Key\":\"4252CFFF2FE50900DAF0F1FF\",\"Value\":1},{\"Key\":\"C92FCFFF75E209009D9FF1FF\",\"Value\":1},{\"Key\":\"B64ACFFF2CE50900A3B2F1FF\",\"Value\":1},{\"Key\":\"0462CFFF2CE509005BBCF1FF\",\"Value\":1},{\"Key\":\"D317CFFF1BEE0900A438F2FF\",\"Value\":1},{\"Key\":\"F185CEFFCBEB0900F906F2FF\",\"Value\":1},{\"Key\":\"44A2CFFF2BE50900E30DF2FF\",\"Value\":1},{\"Key\":\"75CFCEFF4DD90900A769F1FF\",\"Value\":1},{\"Key\":\"7E55CFFF6D000A00BE84F3FF\",\"Value\":1},{\"Key\":\"B55FCDFF5BD7090042B6F0FF\",\"Value\":1},{\"Key\":\"EB48CEFF78DF0900B872F1FF\",\"Value\":1},{\"Key\":\"DB58CEFFD4DC09001667F1FF\",\"Value\":1},{\"Key\":\"29B4CFFF2CE509006A12F2FF\",\"Value\":1},{\"Key\":\"E650CFFFCCFE09002261F3FF\",\"Value\":1},{\"Key\":\"4B54CFFF25EC0900EA91F2FF\",\"Value\":1},{\"Key\":\"4F18CFFF24EE09008745F2FF\",\"Value\":1},{\"Key\":\"D4B8CFFF98D409005F5AF1FF\",\"Value\":1},{\"Key\":\"7287CFFF2CE50900E8BEF1FF\",\"Value\":3},{\"Key\":\"66A0CFFF2CE5090058BCF1FF\",\"Value\":1},{\"Key\":\"186ACFFFFDE009005676F1FF\",\"Value\":1},{\"Key\":\"9379CFFFD5E209008385F1FF\",\"Value\":1},{\"Key\":\"B086CFFF06E40900849AF1FF\",\"Value\":3},{\"Key\":\"F89FCFFF57DD09005F73F1FF\",\"Value\":1},{\"Key\":\"3FAECFFF78E00900E38DF1FF\",\"Value\":1},{\"Key\":\"FAA0CFFF09E10900238AF1FF\",\"Value\":1},{\"Key\":\"197BCFFF2CE50900ABD5F1FF\",\"Value\":1},{\"Key\":\"29C5CFFF96DA0900CB81F1FF\",\"Value\":1},{\"Key\":\"D2E1CFFF7AD80900DB8EF1FF\",\"Value\":1},{\"Key\":\"6FDFCFFFD7D409006B75F1FF\",\"Value\":1},{\"Key\":\"75E8CFFF41DA0900D199F1FF\",\"Value\":1},{\"Key\":\"71C8CFFFE6E109002BA7F1FF\",\"Value\":1},{\"Key\":\"6CA5CFFFADD509000A4CF1FF\",\"Value\":3},{\"Key\":\"4B7CCFFF2CE50900540EF2FF\",\"Value\":1},{\"Key\":\"AB88CFFF2CE50900E2FCF1FF\",\"Value\":1},{\"Key\":\"D56FCFFF2CE5090074ECF1FF\",\"Value\":1},{\"Key\":\"2B61CFFF60E609003618F2FF\",\"Value\":1},{\"Key\":\"7D04CFFF33EC09003AFFF1FF\",\"Value\":1},{\"Key\":\"1C55CFFFF5E709006C20F2FF\",\"Value\":1},{\"Key\":\"8C50CFFFF2EB0900D5BDF2FF\",\"Value\":1},{\"Key\":\"E50ECEFFB3E2090067BCF1FF\",\"Value\":1},{\"Key\":\"8D64CFFFE0EB090058ABF2FF\",\"Value\":1},{\"Key\":\"AEADD0FF84EB0900C299F3FF\",\"Value\":3},{\"Key\":\"33D7CFFF4EF309001244F3FF\",\"Value\":1},{\"Key\":\"E7C6CFFF83F30900B73DF3FF\",\"Value\":1},{\"Key\":\"DCDACFFF81F20900412BF3FF\",\"Value\":1},{\"Key\":\"19C8CFFFFDF209009D2BF3FF\",\"Value\":1},{\"Key\":\"3BC2CFFF36F209002C1CF3FF\",\"Value\":1},{\"Key\":\"3BC2CFFF9AEE0900FBF2F2FF\",\"Value\":1},{\"Key\":\"E0ACCFFFFEFD0900519DF3FF\",\"Value\":1},{\"Key\":\"FBAECFFF3BFC0900368AF3FF\",\"Value\":3},{\"Key\":\"CD21CEFF60E7090004E7F2FF\",\"Value\":3},{\"Key\":\"FACCCFFFACF409007B63F3FF\",\"Value\":3},{\"Key\":\"ED6FCFFFBEFC0900405CF3FF\",\"Value\":1},{\"Key\":\"547ACFFF21FA0900B050F3FF\",\"Value\":1},{\"Key\":\"108FCFFF4AFB0900D068F3FF\",\"Value\":1},{\"Key\":\"A6A0CFFF14F80900D763F3FF\",\"Value\":1},{\"Key\":\"E29BCFFFABF60900F754F3FF\",\"Value\":1},{\"Key\":\"B6B2CFFFDAF309004544F3FF\",\"Value\":1},{\"Key\":\"CDC7CFFFB3F309007151F3FF\",\"Value\":1},{\"Key\":\"31B1CFFF14F00900CBF7F2FF\",\"Value\":1},{\"Key\":\"981FCEFFFFE809003E08F3FF\",\"Value\":3},{\"Key\":\"5913CDFF2D9509006369F3FF\",\"Value\":1},{\"Key\":\"E5EFCFFFA4FC090018CDF3FF\",\"Value\":3},{\"Key\":\"4929D0FF71FA0900ABE5F3FF\",\"Value\":1},{\"Key\":\"A72ED0FF0FFA090023D0F3FF\",\"Value\":3},{\"Key\":\"4426D0FF6CF909008ABFF3FF\",\"Value\":1},{\"Key\":\"6CD9CFFF93FB090092A3F3FF\",\"Value\":1},{\"Key\":\"34EDCFFFA1F90900349DF3FF\",\"Value\":1},{\"Key\":\"1241D0FF15F9090097CDF3FF\",\"Value\":1},{\"Key\":\"4117CFFF10FE09008B8AF3FF\",\"Value\":1},{\"Key\":\"381ECFFFC6FD0900BBAAF3FF\",\"Value\":1},{\"Key\":\"4317CFFF9FFD0900AE9DF3FF\",\"Value\":1},{\"Key\":\"E4CDCFFFA7FD0900DBCCF3FF\",\"Value\":1},{\"Key\":\"EAC3CFFF1FFE09002CBFF3FF\",\"Value\":1},{\"Key\":\"46CACFFFDCF909007D12F4FF\",\"Value\":3},{\"Key\":\"F0ECCFFF63F70900732EF4FF\",\"Value\":3},{\"Key\":\"F8C7CFFFF4FC090049EAF3FF\",\"Value\":1},{\"Key\":\"07B6CFFFA0FD0900B7E5F3FF\",\"Value\":1},{\"Key\":\"93B4CFFF1BFE090080DBF3FF\",\"Value\":1},{\"Key\":\"9110D0FF17F60900602FF4FF\",\"Value\":1},{\"Key\":\"B038D0FF9EF70900E50BF4FF\",\"Value\":3},{\"Key\":\"21E8CFFF63FB09006200F4FF\",\"Value\":1},{\"Key\":\"92EACFFF64F90900AB1AF4FF\",\"Value\":1},{\"Key\":\"2AD8CFFFB2FB090031FCF3FF\",\"Value\":1},{\"Key\":\"7CDDCFFFD3FC090066E7F3FF\",\"Value\":1},{\"Key\":\"63D8CFFF6BFC09000BF0F3FF\",\"Value\":1},{\"Key\":\"BF79CFFFFEFD0900926FF3FF\",\"Value\":1},{\"Key\":\"066CCFFF85FE0900D76AF3FF\",\"Value\":1},{\"Key\":\"973DCFFFFCFE09004B64F3FF\",\"Value\":1},{\"Key\":\"4542CFFF24FE09005256F3FF\",\"Value\":1},{\"Key\":\"E041CFFF4BFC09009843F3FF\",\"Value\":1},{\"Key\":\"0418CFFF06FB0900E943F3FF\",\"Value\":1},{\"Key\":\"C029CFFF94FB0900FC3EF3FF\",\"Value\":1},{\"Key\":\"CB1CCFFF1BF90900202FF3FF\",\"Value\":1},{\"Key\":\"D129CFFFD3FE090030A2F3FF\",\"Value\":1},{\"Key\":\"E638CFFFC8FD090034C3F3FF\",\"Value\":1},{\"Key\":\"D03CCFFFD8FF09000DA2F3FF\",\"Value\":1},{\"Key\":\"9B27CFFF1CF709004BEDF3FF\",\"Value\":3},{\"Key\":\"2754CFFF28FF09002FC3F3FF\",\"Value\":1},{\"Key\":\"F054CFFFFFFF090057B5F3FF\",\"Value\":1},{\"Key\":\"EA3BCFFF8EFB09008CDAF3FF\",\"Value\":1},{\"Key\":\"1763CFFFBE000A007E9DF3FF\",\"Value\":1},{\"Key\":\"696DCFFF90000A00A390F3FF\",\"Value\":1},{\"Key\":\"6979CFFF7B000A0064A2F3FF\",\"Value\":1},{\"Key\":\"907CCFFF8EFF09002584F3FF\",\"Value\":1},{\"Key\":\"E96DCFFF2C000A00B4B5F3FF\",\"Value\":1},{\"Key\":\"4D7FCFFF2F000A00ECB3F3FF\",\"Value\":1},{\"Key\":\"2E4ACFFFB9FC090018D9F3FF\",\"Value\":1},{\"Key\":\"861BCFFF0FFB090012CDF3FF\",\"Value\":1},{\"Key\":\"B800CFFFC6F80900D0CEF3FF\",\"Value\":1},{\"Key\":\"3D0BCFFFF0FB090044B5F3FF\",\"Value\":1},{\"Key\":\"FF1ECFFF68FD0900B0B3F3FF\",\"Value\":1},{\"Key\":\"C9ADD0FF7CED090001DBF3FF\",\"Value\":3},{\"Key\":\"8895D0FF1BF1090022DDF3FF\",\"Value\":3},{\"Key\":\"3BD6D0FF07E8090004BCF3FF\",\"Value\":1},{\"Key\":\"6612D0FF67FB0900F8EFF3FF\",\"Value\":1},{\"Key\":\"91E0CDFF82E4090092E7F2FF\",\"Value\":3},{\"Key\":\"C7F9CFFF6CFB090094FDF3FF\",\"Value\":1},{\"Key\":\"BF59D0FFB6F609007FCDF3FF\",\"Value\":1},{\"Key\":\"E944CFFF02E509004EDCF1FF\",\"Value\":3},{\"Key\":\"5033CFFF36E5090054D7F1FF\",\"Value\":1},{\"Key\":\"342ACFFFB4D80900F079F1FF\",\"Value\":3},{\"Key\":\"3C66CFFF69E509004909F2FF\",\"Value\":1},{\"Key\":\"4217CFFFF8D60900F16EF1FF\",\"Value\":1},{\"Key\":\"CBFFCEFF86D60900B36AF1FF\",\"Value\":1},{\"Key\":\"44ECCEFF9DDF0900D89EF1FF\",\"Value\":3},{\"Key\":\"4588CFFFD9E40900BB1DF2FF\",\"Value\":1},{\"Key\":\"0D1ACFFFADDD0900B7A5F1FF\",\"Value\":1},{\"Key\":\"F808CFFFA1E5090095CBF1FF\",\"Value\":3},{\"Key\":\"C408CFFF23D60900CD45F1FF\",\"Value\":3},{\"Key\":\"63C5CEFFF2D809002F51F1FF\",\"Value\":3},{\"Key\":\"DA1BCFFF51D60900044EF1FF\",\"Value\":1},{\"Key\":\"2351CFFF2CE50900FA97F1FF\",\"Value\":1},{\"Key\":\"1F4BCFFF84D709009837F1FF\",\"Value\":1},{\"Key\":\"6432CFFFA3D709004C50F1FF\",\"Value\":1},{\"Key\":\"2F89CFFF2BE50900A00DF2FF\",\"Value\":1},{\"Key\":\"ED9FCFFF2CE509001BEEF1FF\",\"Value\":1},{\"Key\":\"FBD6CDFFD6E409000214F3FF\",\"Value\":3},{\"Key\":\"3482CDFF78D909003009F3FF\",\"Value\":1},{\"Key\":\"C08FCDFF5CDB0900B013F3FF\",\"Value\":1},{\"Key\":\"98FCCDFF4AE4090093D1F2FF\",\"Value\":1},{\"Key\":\"D937CEFFCFE909005006F3FF\",\"Value\":1},{\"Key\":\"C2F8CDFF47E509001EDFF2FF\",\"Value\":1},{\"Key\":\"4F5CCEFFA8EB0900DF63F3FF\",\"Value\":1},{\"Key\":\"196DCEFF50ED0900616AF3FF\",\"Value\":1},{\"Key\":\"6257CEFFE9EB09003153F3FF\",\"Value\":1},{\"Key\":\"3F71CEFFC6ED09004979F3FF\",\"Value\":1},{\"Key\":\"E483CEFFFFEF0900D668F3FF\",\"Value\":1},{\"Key\":\"7681CEFF08EF0900827DF3FF\",\"Value\":1},{\"Key\":\"116CCEFFCFEE09002090F3FF\",\"Value\":1},{\"Key\":\"215ACEFFFEEB0900AA76F3FF\",\"Value\":1},{\"Key\":\"5B96CEFF16F209005451F3FF\",\"Value\":1},{\"Key\":\"85FDCDFF50E7090038F7F2FF\",\"Value\":1},{\"Key\":\"A137CEFF0BEA0900772FF3FF\",\"Value\":1},{\"Key\":\"AA20CEFFD2E80900612AF3FF\",\"Value\":1},{\"Key\":\"A483CEFF4DF00900C952F3FF\",\"Value\":3},{\"Key\":\"D7B8CEFFD5F2090084B6F3FF\",\"Value\":1},{\"Key\":\"7CAACEFF8BF30900528CF3FF\",\"Value\":1},{\"Key\":\"5520CEFFE7E20900126AF3FF\",\"Value\":3},{\"Key\":\"2990CEFFDCEE09005FA1F3FF\",\"Value\":1},{\"Key\":\"1CA5CEFF36EF090047BBF3FF\",\"Value\":1},{\"Key\":\"7E7DCEFF28EE09009AA0F3FF\",\"Value\":1},{\"Key\":\"D736CEFFD8E609005464F3FF\",\"Value\":1},{\"Key\":\"AF82CEFFA5ED090050B0F3FF\",\"Value\":1},{\"Key\":\"9FA9CEFF74EE090016D7F3FF\",\"Value\":1},{\"Key\":\"7CB7CEFF23F109003DC4F3FF\",\"Value\":1},{\"Key\":\"68CACEFF04F4090074C4F3FF\",\"Value\":1},{\"Key\":\"DBC9CEFF18F1090010DAF3FF\",\"Value\":1},{\"Key\":\"C426CFFF7CF20900CB03F4FF\",\"Value\":1},{\"Key\":\"1101CFFFC8EF090085FFF3FF\",\"Value\":1},{\"Key\":\"8692CEFF3DED090089C9F3FF\",\"Value\":1},{\"Key\":\"1A21CFFFC0ED09001916F4FF\",\"Value\":1},{\"Key\":\"1508CFFF63ED0900FC15F4FF\",\"Value\":1},{\"Key\":\"C9E3CEFF10F70900D5C5F3FF\",\"Value\":1},{\"Key\":\"7BE7CEFFC2EC09005319F4FF\",\"Value\":1},{\"Key\":\"7D54CFFFB4ED09002024F4FF\",\"Value\":1},{\"Key\":\"D545CEFFEDE90900D656F3FF\",\"Value\":1},{\"Key\":\"0045CEFFBFE80900CF64F3FF\",\"Value\":1},{\"Key\":\"BC33CFFF98ED0900632FF4FF\",\"Value\":1},{\"Key\":\"174ACEFF70E709008F77F3FF\",\"Value\":1},{\"Key\":\"B719D1FFD1DC0900DFDDF3FF\",\"Value\":3},{\"Key\":\"1BFAD0FFCCE40900D1C5F3FF\",\"Value\":1},{\"Key\":\"A6F3D0FF10E60900A3B1F3FF\",\"Value\":1},{\"Key\":\"331AD1FF3BE309002AC4F3FF\",\"Value\":1},{\"Key\":\"940AD1FFB0E3090008C3F3FF\",\"Value\":1},{\"Key\":\"C2F7D0FFF7E50900F09CF3FF\",\"Value\":1},{\"Key\":\"790CD1FF58E409007FB5F3FF\",\"Value\":1},{\"Key\":\"0707D1FF23E509001B9EF3FF\",\"Value\":1},{\"Key\":\"443BD0FF2CE509002D5BF2FF\",\"Value\":1},{\"Key\":\"642ACFFF6DFE09006464F3FF\",\"Value\":1},{\"Key\":\"9A19CFFFC7FD0900776AF3FF\",\"Value\":1},{\"Key\":\"B32DCFFF34FF0900C076F3FF\",\"Value\":1},{\"Key\":\"3D29CFFF5BFD09008953F3FF\",\"Value\":1},{\"Key\":\"F8E5CEFFBCF00900B4EDF3FF\",\"Value\":3},{\"Key\":\"DC64CFFFDBF7090048FEF3FF\",\"Value\":1},{\"Key\":\"3449CFFF34F509008001F4FF\",\"Value\":1},{\"Key\":\"DC9DCFFF50F90900BE0BF4FF\",\"Value\":1},{\"Key\":\"91AACFFFD9FA09006206F4FF\",\"Value\":1},{\"Key\":\"B985CFFF83F709007A0BF4FF\",\"Value\":1},{\"Key\":\"2D97CFFFCEF609004216F4FF\",\"Value\":1},{\"Key\":\"CF5CD0FFE5F40900EC15F4FF\",\"Value\":1},{\"Key\":\"896FD0FF67F50900AD01F4FF\",\"Value\":1},{\"Key\":\"CF0FD1FF85C909000E0AF4FF\",\"Value\":1},{\"Key\":\"07E4D0FF1CE50900EFDCF3FF\",\"Value\":1},{\"Key\":\"5B1CCFFFD8FC09000856F3FF\",\"Value\":1},{\"Key\":\"73F0CEFF53F90900F151F3FF\",\"Value\":1},{\"Key\":\"6205CFFFD7FA0900A150F3FF\",\"Value\":1},{\"Key\":\"05DBCEFF82F70900DF53F3FF\",\"Value\":1},{\"Key\":\"B109CFFF6CFC09009065F3FF\",\"Value\":1},{\"Key\":\"A900CEFF3AE00900465BF3FF\",\"Value\":3},{\"Key\":\"6E7BCFFFA6F309006018F4FF\",\"Value\":1},{\"Key\":\"3E88CFFF94EE09009039F4FF\",\"Value\":1},{\"Key\":\"91A0CFFF6B9A09000DADF4FF\",\"Value\":1},{\"Key\":\"A3C5CFFF08EF09009054F4FF\",\"Value\":1},{\"Key\":\"388FCFFF69EC0900875DF4FF\",\"Value\":1},{\"Key\":\"FA9ECFFF5BEA09007261F4FF\",\"Value\":1},{\"Key\":\"EBEACFFF23E709005665F4FF\",\"Value\":1},{\"Key\":\"E44ACFFFF16F09002DCFF4FF\",\"Value\":1},{\"Key\":\"A1D9CFFF52EF09003F4FF4FF\",\"Value\":1},{\"Key\":\"307ACFFFFBEE0900454BF4FF\",\"Value\":1},{\"Key\":\"7330CFFFE37009003CC6F4FF\",\"Value\":1},{\"Key\":\"811BCFFFFA6D09006EC2F4FF\",\"Value\":1},{\"Key\":\"BF16CFFFF1FD09001C78F3FF\",\"Value\":1},{\"Key\":\"C309CFFF1AFD0900557BF3FF\",\"Value\":1},{\"Key\":\"0FB9CDFF67E00900F5E3F2FF\",\"Value\":3},{\"Key\":\"87EBCDFFF8E50900E51BF3FF\",\"Value\":1},{\"Key\":\"F9E9CDFFA4E609009C0AF3FF\",\"Value\":1},{\"Key\":\"8EFECDFFFAE609004819F3FF\",\"Value\":1},{\"Key\":\"C510CEFF3EE709005330F3FF\",\"Value\":1},{\"Key\":\"D80BCEFF54E509001F43F3FF\",\"Value\":1},{\"Key\":\"FB24CEFFFDE709006F40F3FF\",\"Value\":1},{\"Key\":\"9ECACFFFBCF20900FC3DF4FF\",\"Value\":1},{\"Key\":\"2DE9CFFF27F009008C4EF4FF\",\"Value\":1},{\"Key\":\"EA30CFFFE2F109002609F4FF\",\"Value\":1},{\"Key\":\"5333CFFF1BEF09001A17F4FF\",\"Value\":1},{\"Key\":\"72AFCFFF07F00900753DF4FF\",\"Value\":1},{\"Key\":\"8899CFFFADFE09003D92F3FF\",\"Value\":1},{\"Key\":\"3F63D0FF8DF60900C3E6F3FF\",\"Value\":1},{\"Key\":\"9A6FCFFF87EE09001B4BF4FF\",\"Value\":1},{\"Key\":\"F5FCCDFFA3E90900E920F2FF\",\"Value\":1},{\"Key\":\"5EFECDFFCAE80900C10DF2FF\",\"Value\":1},{\"Key\":\"F6F6CDFF72E50900F6F0F1FF\",\"Value\":1},{\"Key\":\"DA09CEFFB3E7090025FFF1FF\",\"Value\":1},{\"Key\":\"9D17CEFFB9E90900F915F2FF\",\"Value\":1},{\"Key\":\"BF22CEFFC9E90900DD16F2FF\",\"Value\":1},{\"Key\":\"4128CEFFE2EA0900432BF2FF\",\"Value\":1},{\"Key\":\"3CBACEFFCAE9090021D8F1FF\",\"Value\":1},{\"Key\":\"85A1CEFF15D70900512CF1FF\",\"Value\":1},{\"Key\":\"6690CEFFDAD309002906F1FF\",\"Value\":1},{\"Key\":\"526CCEFF48DA09009959F1FF\",\"Value\":1},{\"Key\":\"BEA1D0FF96D80900BAFCF1FF\",\"Value\":1},{\"Key\":\"1CAECFFF2CE5090068D7F1FF\",\"Value\":1},{\"Key\":\"16BACFFF2CE5090084E9F1FF\",\"Value\":1},{\"Key\":\"46FFCDFF1DD50900D8EFF0FF\",\"Value\":1},{\"Key\":\"869ECEFFE1DE09002B83F1FF\",\"Value\":3},{\"Key\":\"CC9ECEFFC3E909001ED6F1FF\",\"Value\":3},{\"Key\":\"36DDCEFF6DD809000026F1FF\",\"Value\":1},{\"Key\":\"E9F4CEFF60D60900D153F1FF\",\"Value\":1},{\"Key\":\"28F3CEFF10D70900203AF1FF\",\"Value\":1},{\"Key\":\"30F0CEFF4CD709004E29F1FF\",\"Value\":1},{\"Key\":\"1D15D0FF2CE509005249F2FF\",\"Value\":1},{\"Key\":\"6E22D0FF2CE50900655EF2FF\",\"Value\":1},{\"Key\":\"4D83CEFFBEDF09004D83F1FF\",\"Value\":3},{\"Key\":\"846CCEFFECE609009BB8F1FF\",\"Value\":3},{\"Key\":\"17C2CFFF0CE50900ED49F2FF\",\"Value\":1},{\"Key\":\"61ABCEFFA7EC090077FBF1FF\",\"Value\":3},{\"Key\":\"1A62CEFF4ED709004839F1FF\",\"Value\":3},{\"Key\":\"1BC0CDFF97D70900D153F1FF\",\"Value\":1},{\"Key\":\"B3B6CDFFAFD709009B54F1FF\",\"Value\":1},{\"Key\":\"C19BCDFF42D80900E75BF1FF\",\"Value\":1},{\"Key\":\"1490CDFF06D409002239F1FF\",\"Value\":1},{\"Key\":\"E3B3CDFF65DA0900C774F1FF\",\"Value\":1},{\"Key\":\"6FCECDFF65DB09007483F1FF\",\"Value\":1},{\"Key\":\"B3B3CDFFF8DA0900EC80F1FF\",\"Value\":1},{\"Key\":\"F68ECDFF44D909009D6CF1FF\",\"Value\":1},{\"Key\":\"6090CDFF8DDA09005882F1FF\",\"Value\":1},{\"Key\":\"0E36CDFF66D10900D18EF1FF\",\"Value\":1},{\"Key\":\"004ACDFF65D409007798F1FF\",\"Value\":1},{\"Key\":\"422ECDFFCBCF0900D89AF1FF\",\"Value\":1},{\"Key\":\"14B4CDFF6DDD09003ABEF1FF\",\"Value\":1},{\"Key\":\"84B0CDFF8CDE090020C9F1FF\",\"Value\":1},{\"Key\":\"759CCDFFDDDC090051BDF1FF\",\"Value\":1},{\"Key\":\"3D96CDFFE9DD0900FDC8F1FF\",\"Value\":1},{\"Key\":\"519ACDFFC8FC0600645A0700\",\"Value\":1},{\"Key\":\"C8B6CDFF3AE209004DE8F1FF\",\"Value\":1},{\"Key\":\"DDC5CDFFA5DC0900A3B0F1FF\",\"Value\":1},{\"Key\":\"4583CDFFEFD409005243F1FF\",\"Value\":1},{\"Key\":\"4395CDFFF3D20900C42CF1FF\",\"Value\":1},{\"Key\":\"38E5CDFF81D4090012EEF0FF\",\"Value\":1},{\"Key\":\"3E8FCDFFF9D1090017F1F0FF\",\"Value\":1},{\"Key\":\"1EC5CDFF6DD6090090ECF0FF\",\"Value\":1},{\"Key\":\"7CC0CDFFE1D50900BBDEF0FF\",\"Value\":1},{\"Key\":\"C9ACCDFF61D20900ECE2F0FF\",\"Value\":1},{\"Key\":\"CA50CDFF45D4090035EDF0FF\",\"Value\":1},{\"Key\":\"9F31CDFFF6D70900A9ECF0FF\",\"Value\":1},{\"Key\":\"E945CDFF23D609000409F1FF\",\"Value\":1},{\"Key\":\"103CCDFF5FD60900D60DF1FF\",\"Value\":1},{\"Key\":\"E66CCDFF35E0090090FFF1FF\",\"Value\":1},{\"Key\":\"9608CDFFEB890900389DF3FF\",\"Value\":1},{\"Key\":\"8214CDFF218A090039A0F3FF\",\"Value\":1},{\"Key\":\"8FFFCCFF128609005DC2F3FF\",\"Value\":1},{\"Key\":\"FC2BD3FFC92A0800EEF00000\",\"Value\":1},{\"Key\":\"5E38D3FF2B2908007BD70000\",\"Value\":1},{\"Key\":\"23B2D3FFD42D080077380200\",\"Value\":1},{\"Key\":\"8B3BD3FF2E2B080010820000\",\"Value\":1},{\"Key\":\"2742D3FF0D2B08008B8C0000\",\"Value\":1},{\"Key\":\"1A2DD4FFC54F080082520200\",\"Value\":1},{\"Key\":\"C96AD3FFEE290800AD520100\",\"Value\":3},{\"Key\":\"D70AD4FF8D7308006A8A0200\",\"Value\":1},{\"Key\":\"80F4D3FF2E2B0800E9130200\",\"Value\":1},{\"Key\":\"E81ED4FFE7610800146C0200\",\"Value\":1},{\"Key\":\"A238D4FF10A70800E1E50200\",\"Value\":1},{\"Key\":\"795CD3FF374608003E740200\",\"Value\":1},{\"Key\":\"9F6AD5FF585C08005E53FFFF\",\"Value\":1},{\"Key\":\"235DD5FF795D08002B4DFFFF\",\"Value\":1},{\"Key\":\"623FCFFFFFAA0700D3E6FFFF\",\"Value\":1},{\"Key\":\"8F1ECFFFFFAA070034F8FFFF\",\"Value\":1},{\"Key\":\"9718CFFFFFAA070018E3FFFF\",\"Value\":1},{\"Key\":\"F70BCFFFFFAA070014EDFFFF\",\"Value\":1},{\"Key\":\"4C52CFFF17AB070029C6FFFF\",\"Value\":1},{\"Key\":\"8C35CFFFB8A9070064C7FFFF\",\"Value\":1},{\"Key\":\"E952CFFFFFAA0700C5EEFFFF\",\"Value\":1},{\"Key\":\"B034CFFFC5A80700A5BDFFFF\",\"Value\":1},{\"Key\":\"C822CFFFF1A6070086AFFFFF\",\"Value\":1},{\"Key\":\"4EF5CEFFFFAA0700C7150000\",\"Value\":1},{\"Key\":\"7F0ACFFFFFAA0700CE110000\",\"Value\":1},{\"Key\":\"7305CFFFFFAA0700A3480000\",\"Value\":1},{\"Key\":\"3722CFFFFFAA0700AE1F0000\",\"Value\":1},{\"Key\":\"CB3BCFFFFFAA07007A2A0000\",\"Value\":1},{\"Key\":\"60A9CDFF84FF0600D25B0700\",\"Value\":1},{\"Key\":\"A3A6CCFF0ED20600B0E40700\",\"Value\":1},{\"Key\":\"7722CDFF68E70600165D0700\",\"Value\":1},{\"Key\":\"E449CDFF17F00600E14F0700\",\"Value\":1},{\"Key\":\"22CFCDFF911B0700F6CF0600\",\"Value\":1},{\"Key\":\"593FCDFFAEF1060001390700\",\"Value\":1},{\"Key\":\"1E3ACDFF18F30600732A0700\",\"Value\":1},{\"Key\":\"43A7CCFF98E106001C140700\",\"Value\":1},{\"Key\":\"FD9ACCFF30E20600DE030700\",\"Value\":1},{\"Key\":\"F08FCCFF50E10600C9010700\",\"Value\":1},{\"Key\":\"FB80CCFFA0E2060032E80600\",\"Value\":1},{\"Key\":\"2C76CCFF60E20600A3E10600\",\"Value\":1},{\"Key\":\"3050CCFFBEDF0600A1D00600\",\"Value\":1},{\"Key\":\"F12BCCFF5FDE06000ABB0600\",\"Value\":1},{\"Key\":\"7689B9FFA0FC1000815ABFFF\",\"Value\":1},{\"Key\":\"D049BBFF910111001FD0BDFF\",\"Value\":1},{\"Key\":\"0C39BBFF91011100F0DABDFF\",\"Value\":1},{\"Key\":\"054EBBFF91011100E7B5BDFF\",\"Value\":1},{\"Key\":\"F667BBFFA502110099A6BDFF\",\"Value\":1},{\"Key\":\"D966BBFFA502110029BEBDFF\",\"Value\":1},{\"Key\":\"0677BBFF990211006CBCBDFF\",\"Value\":1},{\"Key\":\"CF7DBBFF66021100A9B6BDFF\",\"Value\":1},{\"Key\":\"E187BBFFB8011100CCACBDFF\",\"Value\":1},{\"Key\":\"E487BBFFA00111001896BDFF\",\"Value\":1},{\"Key\":\"7881BBFF070211000C9BBDFF\",\"Value\":1},{\"Key\":\"AA82BBFFA50211007FE2BDFF\",\"Value\":1},{\"Key\":\"4D89BBFFA5021100F0E3BDFF\",\"Value\":1},{\"Key\":\"2A78BBFFA50211004BEDBDFF\",\"Value\":1},{\"Key\":\"6664BBFF91011100A700BEFF\",\"Value\":1},{\"Key\":\"376ABBFFED0111003F0CBEFF\",\"Value\":1},{\"Key\":\"506FBBFF910111009328BEFF\",\"Value\":1},{\"Key\":\"FE5ABBFF910111008430BEFF\",\"Value\":1},{\"Key\":\"74A6BBFF19011100F5E7BDFF\",\"Value\":1},{\"Key\":\"EBAABBFF07011100ECE1BDFF\",\"Value\":1},{\"Key\":\"14BCBBFF350111007B08BEFF\",\"Value\":1},{\"Key\":\"4ABDBBFF1E0111008FFFBDFF\",\"Value\":1},{\"Key\":\"2FA3BBFF460211003BFEBDFF\",\"Value\":1},{\"Key\":\"6DB4BBFF35011100B210BEFF\",\"Value\":1},{\"Key\":\"B175BEFF93B810009ABCBDFF\",\"Value\":1},{\"Key\":\"DB52BEFF78C3100048D3BDFF\",\"Value\":1},{\"Key\":\"0A72C0FF6F40100005B8BFFF\",\"Value\":1},{\"Key\":\"0345C0FFA551100051D2BFFF\",\"Value\":1},{\"Key\":\"9292C0FF4238100050F7BFFF\",\"Value\":1},{\"Key\":\"7DBDC0FFFA2910006001C0FF\",\"Value\":1},{\"Key\":\"AB03C1FF161310002303C0FF\",\"Value\":1},{\"Key\":\"3DECC4FF06510F00AD01BEFF\",\"Value\":1},{\"Key\":\"CBFCC4FF7A4D0F00C7F4BDFF\",\"Value\":1},{\"Key\":\"B7A3C4FF544E0F007EA6BDFF\",\"Value\":1},{\"Key\":\"9E27C8FF31500F002713C4FF\",\"Value\":1},{\"Key\":\"9BCFC7FF31500F00A153C6FF\",\"Value\":1},{\"Key\":\"20EBC7FF31500F00C85AC6FF\",\"Value\":1},{\"Key\":\"77C4C7FFDF4F0F005D6CC6FF\",\"Value\":1},{\"Key\":\"DBEFCEFF36911000DD2DD3FF\",\"Value\":1},{\"Key\":\"ADEACEFFCF8D1000B318D3FF\",\"Value\":1},{\"Key\":\"B6CACEFFFF871000311ED3FF\",\"Value\":1},{\"Key\":\"D284D3FF86D609000D87F4FF\",\"Value\":1},{\"Key\":\"2D8CD3FF9AD60900ED91F4FF\",\"Value\":1},{\"Key\":\"B18CD3FF58D50900D8B6F4FF\",\"Value\":1},{\"Key\":\"30A0D3FFF3D409004502F5FF\",\"Value\":1}],\"SerializedName\":\"WorldObjectLocatorManager\",\"UniqueFile\":true}"}}